{
    "track_points": [
        {
            "time": "2023-11-03T02:48:07.000Z",
            "latitude": 35.997610094,
            "longitude": 139.18685919200001,
            "altitude": 810
        },
        {
            "time": "2023-11-03T02:48:11.000Z",
            "latitude": 35.997343438,
            "longitude": 139.18704251800003,
            "altitude": 808
        },
        {
            "time": "2023-11-03T02:48:13.000Z",
            "latitude": 35.997226776,
            "longitude": 139.18707584999999,
            "altitude": 807
        },
        {
            "time": "2023-11-03T02:48:15.000Z",
            "latitude": 35.997110113999994,
            "longitude": 139.187125848,
            "altitude": 807
        },
        {
            "time": "2023-11-03T02:48:17.000Z",
            "latitude": 35.996976786000005,
            "longitude": 139.18724250999998,
            "altitude": 803
        },
        {
            "time": "2023-11-03T02:48:19.000Z",
            "latitude": 35.996876789999995,
            "longitude": 139.187275842,
            "altitude": 806
        },
        {
            "time": "2023-11-03T02:48:21.000Z",
            "latitude": 35.996776794,
            "longitude": 139.187309174,
            "altitude": 806
        },
        {
            "time": "2023-11-03T02:48:23.000Z",
            "latitude": 35.9966268,
            "longitude": 139.18732584,
            "altitude": 805
        },
        {
            "time": "2023-11-03T02:48:25.000Z",
            "latitude": 35.99654347,
            "longitude": 139.187309174,
            "altitude": 803
        },
        {
            "time": "2023-11-03T02:48:27.000Z",
            "latitude": 35.99646014,
            "longitude": 139.18734250600002,
            "altitude": 801
        },
        {
            "time": "2023-11-03T02:48:29.000Z",
            "latitude": 35.996343478,
            "longitude": 139.18749250000002,
            "altitude": 799
        },
        {
            "time": "2023-11-03T02:48:31.000Z",
            "latitude": 35.996210149999996,
            "longitude": 139.18762582800002,
            "altitude": 799
        },
        {
            "time": "2023-11-03T02:48:33.000Z",
            "latitude": 35.996160152,
            "longitude": 139.18762582800002,
            "altitude": 798
        },
        {
            "time": "2023-11-03T02:48:35.000Z",
            "latitude": 35.996110154,
            "longitude": 139.187725824,
            "altitude": 798
        },
        {
            "time": "2023-11-03T02:48:37.000Z",
            "latitude": 35.996110154,
            "longitude": 139.187842486,
            "altitude": 797
        },
        {
            "time": "2023-11-03T02:48:39.000Z",
            "latitude": 35.996043490000005,
            "longitude": 139.18795914799998,
            "altitude": 796
        },
        {
            "time": "2023-11-03T02:48:41.000Z",
            "latitude": 35.995926828,
            "longitude": 139.18797581399997,
            "altitude": 798
        },
        {
            "time": "2023-11-03T02:48:43.000Z",
            "latitude": 35.995826832000006,
            "longitude": 139.187892484,
            "altitude": 799
        },
        {
            "time": "2023-11-03T02:48:45.000Z",
            "latitude": 35.995760168,
            "longitude": 139.187725824,
            "altitude": 799
        },
        {
            "time": "2023-11-03T02:48:47.000Z",
            "latitude": 35.995760168,
            "longitude": 139.187542498,
            "altitude": 800
        },
        {
            "time": "2023-11-03T02:48:49.000Z",
            "latitude": 35.995826832000006,
            "longitude": 139.18740917,
            "altitude": 798
        },
        {
            "time": "2023-11-03T02:48:51.000Z",
            "latitude": 35.995926828,
            "longitude": 139.187425836,
            "altitude": 797
        },
        {
            "time": "2023-11-03T02:48:53.000Z",
            "latitude": 35.99596016,
            "longitude": 139.18764249400002,
            "altitude": 797
        },
        {
            "time": "2023-11-03T02:48:57.000Z",
            "latitude": 35.996026824,
            "longitude": 139.18800914599998,
            "altitude": 798
        },
        {
            "time": "2023-11-03T02:48:59.000Z",
            "latitude": 35.995893496,
            "longitude": 139.18810914199997,
            "altitude": 797
        },
        {
            "time": "2023-11-03T02:49:01.000Z",
            "latitude": 35.995826832000006,
            "longitude": 139.188175806,
            "altitude": 795
        },
        {
            "time": "2023-11-03T02:49:03.000Z",
            "latitude": 35.995726835999996,
            "longitude": 139.188275802,
            "altitude": 793
        },
        {
            "time": "2023-11-03T02:49:05.000Z",
            "latitude": 35.995660172,
            "longitude": 139.18840912999997,
            "altitude": 793
        },
        {
            "time": "2023-11-03T02:49:07.000Z",
            "latitude": 35.99562684,
            "longitude": 139.188609122,
            "altitude": 791
        },
        {
            "time": "2023-11-03T02:49:09.000Z",
            "latitude": 35.99554351,
            "longitude": 139.18869245200003,
            "altitude": 788
        },
        {
            "time": "2023-11-03T02:49:11.000Z",
            "latitude": 35.995410182,
            "longitude": 139.18865912,
            "altitude": 789
        },
        {
            "time": "2023-11-03T02:49:13.000Z",
            "latitude": 35.995343518000006,
            "longitude": 139.188459128,
            "altitude": 786
        },
        {
            "time": "2023-11-03T02:49:15.000Z",
            "latitude": 35.995310186,
            "longitude": 139.18824247000003,
            "altitude": 783
        },
        {
            "time": "2023-11-03T02:49:17.000Z",
            "latitude": 35.99521019,
            "longitude": 139.18810914199997,
            "altitude": 779
        },
        {
            "time": "2023-11-03T02:49:19.000Z",
            "latitude": 35.995110194000006,
            "longitude": 139.18800914599998,
            "altitude": 778
        },
        {
            "time": "2023-11-03T02:49:21.000Z",
            "latitude": 35.995076862000005,
            "longitude": 139.18824247000003,
            "altitude": 779
        },
        {
            "time": "2023-11-03T02:49:23.000Z",
            "latitude": 35.995060196,
            "longitude": 139.18840912999997,
            "altitude": 778
        },
        {
            "time": "2023-11-03T02:49:25.000Z",
            "latitude": 35.995093528,
            "longitude": 139.18855912399997,
            "altitude": 778
        },
        {
            "time": "2023-11-03T02:49:27.000Z",
            "latitude": 35.995076862000005,
            "longitude": 139.18865912,
            "altitude": 776
        },
        {
            "time": "2023-11-03T02:49:29.000Z",
            "latitude": 35.995026863999996,
            "longitude": 139.188809114,
            "altitude": 775
        },
        {
            "time": "2023-11-03T02:49:31.000Z",
            "latitude": 35.9949602,
            "longitude": 139.188959108,
            "altitude": 773
        },
        {
            "time": "2023-11-03T02:49:33.000Z",
            "latitude": 35.994926868,
            "longitude": 139.189109102,
            "altitude": 774
        },
        {
            "time": "2023-11-03T02:49:35.000Z",
            "latitude": 35.994860204000005,
            "longitude": 139.18929242800002,
            "altitude": 773
        },
        {
            "time": "2023-11-03T02:49:37.000Z",
            "latitude": 35.994810206000004,
            "longitude": 139.18947575399997,
            "altitude": 774
        },
        {
            "time": "2023-11-03T02:49:39.000Z",
            "latitude": 35.994743542,
            "longitude": 139.18960908199998,
            "altitude": 775
        },
        {
            "time": "2023-11-03T02:49:41.000Z",
            "latitude": 35.994693544,
            "longitude": 139.18972574400001,
            "altitude": 776
        },
        {
            "time": "2023-11-03T02:49:45.000Z",
            "latitude": 35.994593548000005,
            "longitude": 139.19000906600002,
            "altitude": 787
        },
        {
            "time": "2023-11-03T02:49:47.000Z",
            "latitude": 35.994560216,
            "longitude": 139.19004239800003,
            "altitude": 783
        },
        {
            "time": "2023-11-03T02:49:49.000Z",
            "latitude": 35.994426888,
            "longitude": 139.18989240400003,
            "altitude": 775
        },
        {
            "time": "2023-11-03T02:49:51.000Z",
            "latitude": 35.99437689,
            "longitude": 139.18974241000004,
            "altitude": 767
        },
        {
            "time": "2023-11-03T02:49:53.000Z",
            "latitude": 35.99444355400001,
            "longitude": 139.189625748,
            "altitude": 764
        },
        {
            "time": "2023-11-03T02:49:55.000Z",
            "latitude": 35.994610214,
            "longitude": 139.189392424,
            "altitude": 757
        },
        {
            "time": "2023-11-03T02:49:57.000Z",
            "latitude": 35.994660212,
            "longitude": 139.18915909999998,
            "altitude": 753
        },
        {
            "time": "2023-11-03T02:49:59.000Z",
            "latitude": 35.994493551999994,
            "longitude": 139.18912576800003,
            "altitude": 753
        },
        {
            "time": "2023-11-03T02:50:01.000Z",
            "latitude": 35.994343558,
            "longitude": 139.189092436,
            "altitude": 752
        },
        {
            "time": "2023-11-03T02:50:03.000Z",
            "latitude": 35.994243562,
            "longitude": 139.189059104,
            "altitude": 747
        },
        {
            "time": "2023-11-03T02:50:05.000Z",
            "latitude": 35.994143566000005,
            "longitude": 139.189109102,
            "altitude": 745
        },
        {
            "time": "2023-11-03T02:50:07.000Z",
            "latitude": 35.994026904,
            "longitude": 139.189209098,
            "altitude": 743
        },
        {
            "time": "2023-11-03T02:50:09.000Z",
            "latitude": 35.993893576,
            "longitude": 139.18930909399998,
            "altitude": 740
        },
        {
            "time": "2023-11-03T02:50:11.000Z",
            "latitude": 35.99377691400001,
            "longitude": 139.18942575600002,
            "altitude": 739
        },
        {
            "time": "2023-11-03T02:50:13.000Z",
            "latitude": 35.993676918,
            "longitude": 139.189509086,
            "altitude": 739
        },
        {
            "time": "2023-11-03T02:50:15.000Z",
            "latitude": 35.993560255999995,
            "longitude": 139.18960908199998,
            "altitude": 739
        },
        {
            "time": "2023-11-03T02:50:17.000Z",
            "latitude": 35.99346026,
            "longitude": 139.18965907999998,
            "altitude": 740
        },
        {
            "time": "2023-11-03T02:50:19.000Z",
            "latitude": 35.993343597999996,
            "longitude": 139.189675746,
            "altitude": 734
        },
        {
            "time": "2023-11-03T02:50:21.000Z",
            "latitude": 35.993226936,
            "longitude": 139.189792408,
            "altitude": 734
        },
        {
            "time": "2023-11-03T02:50:23.000Z",
            "latitude": 35.993110273999996,
            "longitude": 139.189875738,
            "altitude": 735
        },
        {
            "time": "2023-11-03T02:50:25.000Z",
            "latitude": 35.99296028,
            "longitude": 139.189975734,
            "altitude": 735
        },
        {
            "time": "2023-11-03T02:50:27.000Z",
            "latitude": 35.992810285999994,
            "longitude": 139.19000906600002,
            "altitude": 735
        },
        {
            "time": "2023-11-03T02:50:29.000Z",
            "latitude": 35.99271029,
            "longitude": 139.18989240400003,
            "altitude": 734
        },
        {
            "time": "2023-11-03T02:50:31.000Z",
            "latitude": 35.992610294,
            "longitude": 139.18972574400001,
            "altitude": 731
        },
        {
            "time": "2023-11-03T02:50:33.000Z",
            "latitude": 35.992526964,
            "longitude": 139.18957575000002,
            "altitude": 730
        },
        {
            "time": "2023-11-03T02:50:35.000Z",
            "latitude": 35.992560296,
            "longitude": 139.189359092,
            "altitude": 730
        },
        {
            "time": "2023-11-03T02:50:37.000Z",
            "latitude": 35.992676958,
            "longitude": 139.189359092,
            "altitude": 725
        },
        {
            "time": "2023-11-03T02:50:39.000Z",
            "latitude": 35.99271029,
            "longitude": 139.189509086,
            "altitude": 722
        },
        {
            "time": "2023-11-03T02:50:41.000Z",
            "latitude": 35.992660292,
            "longitude": 139.18965907999998,
            "altitude": 721
        },
        {
            "time": "2023-11-03T02:50:43.000Z",
            "latitude": 35.992593627999995,
            "longitude": 139.189809074,
            "altitude": 722
        },
        {
            "time": "2023-11-03T02:50:45.000Z",
            "latitude": 35.992493632,
            "longitude": 139.18985907200002,
            "altitude": 720
        },
        {
            "time": "2023-11-03T02:50:47.000Z",
            "latitude": 35.992360303999995,
            "longitude": 139.18982574,
            "altitude": 719
        },
        {
            "time": "2023-11-03T02:50:49.000Z",
            "latitude": 35.992260308,
            "longitude": 139.189675746,
            "altitude": 721
        },
        {
            "time": "2023-11-03T02:50:51.000Z",
            "latitude": 35.992243642000005,
            "longitude": 139.18947575399997,
            "altitude": 717
        },
        {
            "time": "2023-11-03T02:50:53.000Z",
            "latitude": 35.992193644000004,
            "longitude": 139.189392424,
            "altitude": 717
        },
        {
            "time": "2023-11-03T02:50:57.000Z",
            "latitude": 35.992010318,
            "longitude": 139.189642414,
            "altitude": 716
        },
        {
            "time": "2023-11-03T02:50:59.000Z",
            "latitude": 35.991993652,
            "longitude": 139.189509086,
            "altitude": 716
        },
        {
            "time": "2023-11-03T02:51:01.000Z",
            "latitude": 35.992176977999996,
            "longitude": 139.189342426,
            "altitude": 713
        },
        {
            "time": "2023-11-03T02:51:03.000Z",
            "latitude": 35.992343638,
            "longitude": 139.18929242800002,
            "altitude": 711
        },
        {
            "time": "2023-11-03T02:51:05.000Z",
            "latitude": 35.992443634,
            "longitude": 139.189342426,
            "altitude": 713
        },
        {
            "time": "2023-11-03T02:51:07.000Z",
            "latitude": 35.992410301999996,
            "longitude": 139.18932575999997,
            "altitude": 710
        },
        {
            "time": "2023-11-03T02:51:09.000Z",
            "latitude": 35.992310306,
            "longitude": 139.18917576599998,
            "altitude": 704
        },
        {
            "time": "2023-11-03T02:51:11.000Z",
            "latitude": 35.992276974000006,
            "longitude": 139.188959108,
            "altitude": 701
        },
        {
            "time": "2023-11-03T02:51:13.000Z",
            "latitude": 35.992310306,
            "longitude": 139.18869245200003,
            "altitude": 699
        },
        {
            "time": "2023-11-03T02:51:15.000Z",
            "latitude": 35.992276974000006,
            "longitude": 139.188475794,
            "altitude": 697
        },
        {
            "time": "2023-11-03T02:51:17.000Z",
            "latitude": 35.992326971999994,
            "longitude": 139.188225804,
            "altitude": 691
        },
        {
            "time": "2023-11-03T02:51:19.000Z",
            "latitude": 35.992410301999996,
            "longitude": 139.187942482,
            "altitude": 684
        },
        {
            "time": "2023-11-03T02:51:21.000Z",
            "latitude": 35.992426968000004,
            "longitude": 139.18765915999998,
            "altitude": 683
        },
        {
            "time": "2023-11-03T02:51:23.000Z",
            "latitude": 35.992426968000004,
            "longitude": 139.18739250399997,
            "altitude": 683
        },
        {
            "time": "2023-11-03T02:51:25.000Z",
            "latitude": 35.992476966,
            "longitude": 139.18722584399998,
            "altitude": 687
        },
        {
            "time": "2023-11-03T02:51:27.000Z",
            "latitude": 35.99254363000001,
            "longitude": 139.187109182,
            "altitude": 686
        },
        {
            "time": "2023-11-03T02:51:29.000Z",
            "latitude": 35.992626959999996,
            "longitude": 139.18694252199998,
            "altitude": 685
        },
        {
            "time": "2023-11-03T02:51:31.000Z",
            "latitude": 35.99271029,
            "longitude": 139.18675919600003,
            "altitude": 682
        },
        {
            "time": "2023-11-03T02:51:33.000Z",
            "latitude": 35.992693624000005,
            "longitude": 139.18655920400002,
            "altitude": 682
        },
        {
            "time": "2023-11-03T02:51:35.000Z",
            "latitude": 35.992643626,
            "longitude": 139.18640921,
            "altitude": 678
        },
        {
            "time": "2023-11-03T02:51:37.000Z",
            "latitude": 35.992593627999995,
            "longitude": 139.186259216,
            "altitude": 677
        },
        {
            "time": "2023-11-03T02:51:39.000Z",
            "latitude": 35.992610294,
            "longitude": 139.186042558,
            "altitude": 677
        },
        {
            "time": "2023-11-03T02:51:41.000Z",
            "latitude": 35.99251029799999,
            "longitude": 139.185859232,
            "altitude": 674
        },
        {
            "time": "2023-11-03T02:51:43.000Z",
            "latitude": 35.99251029799999,
            "longitude": 139.185675906,
            "altitude": 674
        },
        {
            "time": "2023-11-03T02:51:45.000Z",
            "latitude": 35.992560296,
            "longitude": 139.185459248,
            "altitude": 672
        },
        {
            "time": "2023-11-03T02:51:47.000Z",
            "latitude": 35.99251029799999,
            "longitude": 139.18524259,
            "altitude": 670
        },
        {
            "time": "2023-11-03T02:51:49.000Z",
            "latitude": 35.992526964,
            "longitude": 139.185025932,
            "altitude": 671
        },
        {
            "time": "2023-11-03T02:51:51.000Z",
            "latitude": 35.99251029799999,
            "longitude": 139.184875938,
            "altitude": 671
        },
        {
            "time": "2023-11-03T02:51:53.000Z",
            "latitude": 35.992443634,
            "longitude": 139.18470927799999,
            "altitude": 672
        },
        {
            "time": "2023-11-03T02:51:55.000Z",
            "latitude": 35.99237697,
            "longitude": 139.18457594999998,
            "altitude": 672
        },
        {
            "time": "2023-11-03T02:51:57.000Z",
            "latitude": 35.992326971999994,
            "longitude": 139.18442595599998,
            "altitude": 671
        },
        {
            "time": "2023-11-03T02:51:59.000Z",
            "latitude": 35.99229364,
            "longitude": 139.184275962,
            "altitude": 670
        },
        {
            "time": "2023-11-03T02:52:01.000Z",
            "latitude": 35.992243642000005,
            "longitude": 139.184125968,
            "altitude": 671
        },
        {
            "time": "2023-11-03T02:52:03.000Z",
            "latitude": 35.992176977999996,
            "longitude": 139.183975974,
            "altitude": 672
        },
        {
            "time": "2023-11-03T02:52:05.000Z",
            "latitude": 35.992110313999994,
            "longitude": 139.183859312,
            "altitude": 671
        },
        {
            "time": "2023-11-03T02:52:07.000Z",
            "latitude": 35.99204365,
            "longitude": 139.183709318,
            "altitude": 670
        },
        {
            "time": "2023-11-03T02:52:09.000Z",
            "latitude": 35.991993652,
            "longitude": 139.18355932400002,
            "altitude": 669
        },
        {
            "time": "2023-11-03T02:52:11.000Z",
            "latitude": 35.991910322,
            "longitude": 139.18345932800003,
            "altitude": 667
        },
        {
            "time": "2023-11-03T02:52:13.000Z",
            "latitude": 35.991826992,
            "longitude": 139.183342666,
            "altitude": 662
        },
        {
            "time": "2023-11-03T02:52:15.000Z",
            "latitude": 35.991693663999996,
            "longitude": 139.18324267,
            "altitude": 661
        },
        {
            "time": "2023-11-03T02:52:17.000Z",
            "latitude": 35.99157700200001,
            "longitude": 139.183109342,
            "altitude": 659
        },
        {
            "time": "2023-11-03T02:52:19.000Z",
            "latitude": 35.99146034,
            "longitude": 139.18297601400002,
            "altitude": 657
        },
        {
            "time": "2023-11-03T02:52:21.000Z",
            "latitude": 35.99136034399999,
            "longitude": 139.182809354,
            "altitude": 653
        },
        {
            "time": "2023-11-03T02:52:23.000Z",
            "latitude": 35.991243682,
            "longitude": 139.18269269200002,
            "altitude": 650
        },
        {
            "time": "2023-11-03T02:52:25.000Z",
            "latitude": 35.99109368799999,
            "longitude": 139.182609362,
            "altitude": 649
        },
        {
            "time": "2023-11-03T02:52:27.000Z",
            "latitude": 35.99096036,
            "longitude": 139.182526032,
            "altitude": 649
        },
        {
            "time": "2023-11-03T02:52:29.000Z",
            "latitude": 35.99086036400001,
            "longitude": 139.18244270199997,
            "altitude": 647
        },
        {
            "time": "2023-11-03T02:52:31.000Z",
            "latitude": 35.990727035999996,
            "longitude": 139.182376038,
            "altitude": 644
        },
        {
            "time": "2023-11-03T02:52:33.000Z",
            "latitude": 35.990577042,
            "longitude": 139.18225937600002,
            "altitude": 643
        },
        {
            "time": "2023-11-03T02:52:35.000Z",
            "latitude": 35.990427047999994,
            "longitude": 139.182192712,
            "altitude": 643
        },
        {
            "time": "2023-11-03T02:52:37.000Z",
            "latitude": 35.990277053999996,
            "longitude": 139.18210938200002,
            "altitude": 645
        },
        {
            "time": "2023-11-03T02:52:39.000Z",
            "latitude": 35.990143726,
            "longitude": 139.18200938599998,
            "altitude": 645
        },
        {
            "time": "2023-11-03T02:52:41.000Z",
            "latitude": 35.990010397999995,
            "longitude": 139.181926056,
            "altitude": 645
        },
        {
            "time": "2023-11-03T02:52:43.000Z",
            "latitude": 35.989893736000006,
            "longitude": 139.18185939199998,
            "altitude": 645
        },
        {
            "time": "2023-11-03T02:52:45.000Z",
            "latitude": 35.989793739999996,
            "longitude": 139.18174273,
            "altitude": 646
        },
        {
            "time": "2023-11-03T02:52:47.000Z",
            "latitude": 35.989693744,
            "longitude": 139.181626068,
            "altitude": 645
        },
        {
            "time": "2023-11-03T02:52:49.000Z",
            "latitude": 35.989593748000004,
            "longitude": 139.181542738,
            "altitude": 644
        },
        {
            "time": "2023-11-03T02:52:51.000Z",
            "latitude": 35.98946042,
            "longitude": 139.18147607400002,
            "altitude": 643
        },
        {
            "time": "2023-11-03T02:52:53.000Z",
            "latitude": 35.989327092,
            "longitude": 139.181342746,
            "altitude": 641
        },
        {
            "time": "2023-11-03T02:52:57.000Z",
            "latitude": 35.989093768,
            "longitude": 139.181259416,
            "altitude": 639
        },
        {
            "time": "2023-11-03T02:52:59.000Z",
            "latitude": 35.988977106,
            "longitude": 139.181342746,
            "altitude": 637
        },
        {
            "time": "2023-11-03T02:53:01.000Z",
            "latitude": 35.988927108000006,
            "longitude": 139.181509406,
            "altitude": 636
        },
        {
            "time": "2023-11-03T02:53:05.000Z",
            "latitude": 35.989010437999994,
            "longitude": 139.18172606399997,
            "altitude": 637
        },
        {
            "time": "2023-11-03T02:53:07.000Z",
            "latitude": 35.989160432,
            "longitude": 139.18180939400003,
            "altitude": 634
        },
        {
            "time": "2023-11-03T02:53:09.000Z",
            "latitude": 35.989343758,
            "longitude": 139.181892724,
            "altitude": 633
        },
        {
            "time": "2023-11-03T02:53:11.000Z",
            "latitude": 35.989527083999995,
            "longitude": 139.18199271999998,
            "altitude": 631
        },
        {
            "time": "2023-11-03T02:53:13.000Z",
            "latitude": 35.98967707799999,
            "longitude": 139.18207605,
            "altitude": 629
        },
        {
            "time": "2023-11-03T02:53:15.000Z",
            "latitude": 35.989827072,
            "longitude": 139.182209378,
            "altitude": 631
        },
        {
            "time": "2023-11-03T02:53:17.000Z",
            "latitude": 35.9899604,
            "longitude": 139.182342706,
            "altitude": 633
        },
        {
            "time": "2023-11-03T02:53:19.000Z",
            "latitude": 35.990110394000006,
            "longitude": 139.18240937000002,
            "altitude": 631
        },
        {
            "time": "2023-11-03T02:53:21.000Z",
            "latitude": 35.990260388,
            "longitude": 139.18244270199997,
            "altitude": 630
        },
        {
            "time": "2023-11-03T02:53:23.000Z",
            "latitude": 35.990410382,
            "longitude": 139.182559364,
            "altitude": 630
        },
        {
            "time": "2023-11-03T02:53:25.000Z",
            "latitude": 35.99054371,
            "longitude": 139.18265936,
            "altitude": 629
        },
        {
            "time": "2023-11-03T02:53:27.000Z",
            "latitude": 35.990677038,
            "longitude": 139.182792688,
            "altitude": 630
        },
        {
            "time": "2023-11-03T02:53:29.000Z",
            "latitude": 35.990810366,
            "longitude": 139.18289268399997,
            "altitude": 626
        },
        {
            "time": "2023-11-03T02:53:31.000Z",
            "latitude": 35.99096036,
            "longitude": 139.183009346,
            "altitude": 627
        },
        {
            "time": "2023-11-03T02:53:33.000Z",
            "latitude": 35.991110354,
            "longitude": 139.18312600800002,
            "altitude": 626
        },
        {
            "time": "2023-11-03T02:53:35.000Z",
            "latitude": 35.991277014000005,
            "longitude": 139.183192672,
            "altitude": 626
        },
        {
            "time": "2023-11-03T02:53:37.000Z",
            "latitude": 35.991427008,
            "longitude": 139.18330933400003,
            "altitude": 621
        },
        {
            "time": "2023-11-03T02:53:39.000Z",
            "latitude": 35.991510338,
            "longitude": 139.18345932800003,
            "altitude": 621
        },
        {
            "time": "2023-11-03T02:53:41.000Z",
            "latitude": 35.99154367,
            "longitude": 139.183592656,
            "altitude": 621
        },
        {
            "time": "2023-11-03T02:53:43.000Z",
            "latitude": 35.991443673999996,
            "longitude": 139.18375931600002,
            "altitude": 621
        },
        {
            "time": "2023-11-03T02:53:45.000Z",
            "latitude": 35.99137701,
            "longitude": 139.183859312,
            "altitude": 618
        },
        {
            "time": "2023-11-03T02:53:47.000Z",
            "latitude": 35.991260348,
            "longitude": 139.18394264199998,
            "altitude": 615
        },
        {
            "time": "2023-11-03T02:53:49.000Z",
            "latitude": 35.991143686,
            "longitude": 139.18399263999999,
            "altitude": 615
        },
        {
            "time": "2023-11-03T02:53:51.000Z",
            "latitude": 35.991043690000005,
            "longitude": 139.184009306,
            "altitude": 612
        },
        {
            "time": "2023-11-03T02:53:53.000Z",
            "latitude": 35.990927028,
            "longitude": 139.183975974,
            "altitude": 611
        },
        {
            "time": "2023-11-03T02:53:55.000Z",
            "latitude": 35.990827032000006,
            "longitude": 139.18392597599998,
            "altitude": 608
        },
        {
            "time": "2023-11-03T02:53:57.000Z",
            "latitude": 35.99071037,
            "longitude": 139.18392597599998,
            "altitude": 606
        },
        {
            "time": "2023-11-03T02:53:59.000Z",
            "latitude": 35.99061037399999,
            "longitude": 139.18389264400003,
            "altitude": 604
        },
        {
            "time": "2023-11-03T02:54:01.000Z",
            "latitude": 35.990477046,
            "longitude": 139.183875978,
            "altitude": 603
        },
        {
            "time": "2023-11-03T02:54:03.000Z",
            "latitude": 35.990343718000005,
            "longitude": 139.183859312,
            "altitude": 602
        },
        {
            "time": "2023-11-03T02:54:05.000Z",
            "latitude": 35.990227056,
            "longitude": 139.183842646,
            "altitude": 602
        },
        {
            "time": "2023-11-03T02:54:07.000Z",
            "latitude": 35.990110394000006,
            "longitude": 139.183859312,
            "altitude": 601
        },
        {
            "time": "2023-11-03T02:54:09.000Z",
            "latitude": 35.989977065999994,
            "longitude": 139.183875978,
            "altitude": 600
        },
        {
            "time": "2023-11-03T02:54:11.000Z",
            "latitude": 35.989860404000005,
            "longitude": 139.18389264400003,
            "altitude": 599
        },
        {
            "time": "2023-11-03T02:54:15.000Z",
            "latitude": 35.989627080000005,
            "longitude": 139.18390931000002,
            "altitude": 598
        },
        {
            "time": "2023-11-03T02:54:17.000Z",
            "latitude": 35.989527083999995,
            "longitude": 139.183975974,
            "altitude": 595
        },
        {
            "time": "2023-11-03T02:54:19.000Z",
            "latitude": 35.989510418,
            "longitude": 139.184125968,
            "altitude": 592
        },
        {
            "time": "2023-11-03T02:54:21.000Z",
            "latitude": 35.989527083999995,
            "longitude": 139.18434262600002,
            "altitude": 591
        },
        {
            "time": "2023-11-03T02:54:23.000Z",
            "latitude": 35.989477086,
            "longitude": 139.184509286,
            "altitude": 591
        },
        {
            "time": "2023-11-03T02:54:25.000Z",
            "latitude": 35.98946042,
            "longitude": 139.18465928000003,
            "altitude": 589
        },
        {
            "time": "2023-11-03T02:54:27.000Z",
            "latitude": 35.989427088,
            "longitude": 139.18480927400003,
            "altitude": 587
        },
        {
            "time": "2023-11-03T02:54:29.000Z",
            "latitude": 35.989360424000004,
            "longitude": 139.18495926800003,
            "altitude": 585
        },
        {
            "time": "2023-11-03T02:54:31.000Z",
            "latitude": 35.989327092,
            "longitude": 139.18514259399998,
            "altitude": 582
        },
        {
            "time": "2023-11-03T02:54:33.000Z",
            "latitude": 35.989277093999995,
            "longitude": 139.18529258799998,
            "altitude": 579
        },
        {
            "time": "2023-11-03T02:54:35.000Z",
            "latitude": 35.989243762,
            "longitude": 139.18542591599999,
            "altitude": 580
        },
        {
            "time": "2023-11-03T02:54:37.000Z",
            "latitude": 35.989243762,
            "longitude": 139.18555924400002,
            "altitude": 578
        },
        {
            "time": "2023-11-03T02:54:39.000Z",
            "latitude": 35.98929376,
            "longitude": 139.18570923800002,
            "altitude": 574
        },
        {
            "time": "2023-11-03T02:54:41.000Z",
            "latitude": 35.98937709,
            "longitude": 139.185809234,
            "altitude": 570
        },
        {
            "time": "2023-11-03T02:54:43.000Z",
            "latitude": 35.989493751999994,
            "longitude": 139.185792568,
            "altitude": 566
        },
        {
            "time": "2023-11-03T02:54:45.000Z",
            "latitude": 35.989643746,
            "longitude": 139.185475914,
            "altitude": 562
        },
        {
            "time": "2023-11-03T02:54:47.000Z",
            "latitude": 35.989693744,
            "longitude": 139.185225924,
            "altitude": 561
        },
        {
            "time": "2023-11-03T02:54:49.000Z",
            "latitude": 35.989793739999996,
            "longitude": 139.185092596,
            "altitude": 559
        },
        {
            "time": "2023-11-03T02:54:51.000Z",
            "latitude": 35.989927068,
            "longitude": 139.184925936,
            "altitude": 555
        },
        {
            "time": "2023-11-03T02:54:53.000Z",
            "latitude": 35.990093728,
            "longitude": 139.18477594200002,
            "altitude": 551
        },
        {
            "time": "2023-11-03T02:54:57.000Z",
            "latitude": 35.990427047999994,
            "longitude": 139.184725944,
            "altitude": 546
        },
        {
            "time": "2023-11-03T02:54:59.000Z",
            "latitude": 35.99061037399999,
            "longitude": 139.18477594200002,
            "altitude": 543
        },
        {
            "time": "2023-11-03T02:55:01.000Z",
            "latitude": 35.990693703999995,
            "longitude": 139.184875938,
            "altitude": 537
        },
        {
            "time": "2023-11-03T02:55:03.000Z",
            "latitude": 35.9907937,
            "longitude": 139.185042598,
            "altitude": 535
        },
        {
            "time": "2023-11-03T02:55:05.000Z",
            "latitude": 35.99087703,
            "longitude": 139.18520925800001,
            "altitude": 535
        },
        {
            "time": "2023-11-03T02:55:07.000Z",
            "latitude": 35.990893696,
            "longitude": 139.185375918,
            "altitude": 535
        },
        {
            "time": "2023-11-03T02:55:09.000Z",
            "latitude": 35.99086036400001,
            "longitude": 139.18557590999998,
            "altitude": 532
        },
        {
            "time": "2023-11-03T02:55:11.000Z",
            "latitude": 35.990810366,
            "longitude": 139.185775902,
            "altitude": 532
        },
        {
            "time": "2023-11-03T02:55:13.000Z",
            "latitude": 35.990777034000004,
            "longitude": 139.185925896,
            "altitude": 531
        },
        {
            "time": "2023-11-03T02:55:15.000Z",
            "latitude": 35.990760368,
            "longitude": 139.186042558,
            "altitude": 532
        },
        {
            "time": "2023-11-03T02:55:17.000Z",
            "latitude": 35.990743702,
            "longitude": 139.18607588999998,
            "altitude": 531
        },
        {
            "time": "2023-11-03T02:55:19.000Z",
            "latitude": 35.990743702,
            "longitude": 139.18607588999998,
            "altitude": 528
        },
        {
            "time": "2023-11-03T02:55:21.000Z",
            "latitude": 35.990777034000004,
            "longitude": 139.18607588999998,
            "altitude": 526
        },
        {
            "time": "2023-11-03T02:55:25.000Z",
            "latitude": 35.990777034000004,
            "longitude": 139.186059224,
            "altitude": 526
        },
        {
            "time": "2023-11-03T02:55:27.000Z",
            "latitude": 35.990760368,
            "longitude": 139.186059224,
            "altitude": 527
        },
        {
            "time": "2023-11-03T02:55:29.000Z",
            "latitude": 35.990777034000004,
            "longitude": 139.186059224,
            "altitude": 527
        },
        {
            "time": "2023-11-03T02:55:31.000Z",
            "latitude": 35.990777034000004,
            "longitude": 139.186042558,
            "altitude": 528
        },
        {
            "time": "2023-11-03T02:55:33.000Z",
            "latitude": 35.990777034000004,
            "longitude": 139.186042558,
            "altitude": 528
        },
        {
            "time": "2023-11-03T02:55:35.000Z",
            "latitude": 35.990777034000004,
            "longitude": 139.186042558,
            "altitude": 528
        },
        {
            "time": "2023-11-03T02:55:37.000Z",
            "latitude": 35.9907937,
            "longitude": 139.186059224,
            "altitude": 528
        },
        {
            "time": "2023-11-03T02:55:39.000Z",
            "latitude": 35.990777034000004,
            "longitude": 139.186059224,
            "altitude": 528
        },
        {
            "time": "2023-11-03T02:55:41.000Z",
            "latitude": 35.990777034000004,
            "longitude": 139.18607588999998,
            "altitude": 527
        },
        {
            "time": "2023-11-03T02:55:43.000Z",
            "latitude": 35.9907937,
            "longitude": 139.18607588999998,
            "altitude": 527
        },
        {
            "time": "2023-11-03T02:55:45.000Z",
            "latitude": 35.9907937,
            "longitude": 139.186109222,
            "altitude": 526
        },
        {
            "time": "2023-11-03T02:55:47.000Z",
            "latitude": 35.990777034000004,
            "longitude": 139.18612588800002,
            "altitude": 525
        },
        {
            "time": "2023-11-03T02:55:49.000Z",
            "latitude": 35.990777034000004,
            "longitude": 139.18617588599997,
            "altitude": 525
        },
        {
            "time": "2023-11-03T02:55:53.000Z",
            "latitude": 35.990743702,
            "longitude": 139.18624255,
            "altitude": 525
        },
        {
            "time": "2023-11-03T02:55:55.000Z",
            "latitude": 35.99071037,
            "longitude": 139.18627588200002,
            "altitude": 526
        },
        {
            "time": "2023-11-03T02:55:57.000Z",
            "latitude": 35.990693703999995,
            "longitude": 139.18630921400003,
            "altitude": 527
        },
        {
            "time": "2023-11-03T02:55:59.000Z",
            "latitude": 35.990677038,
            "longitude": 139.186342546,
            "altitude": 527
        },
        {
            "time": "2023-11-03T02:56:01.000Z",
            "latitude": 35.99064370600001,
            "longitude": 139.186375878,
            "altitude": 528
        },
        {
            "time": "2023-11-03T02:56:03.000Z",
            "latitude": 35.99061037399999,
            "longitude": 139.186392544,
            "altitude": 527
        },
        {
            "time": "2023-11-03T02:56:05.000Z",
            "latitude": 35.990577042,
            "longitude": 139.186392544,
            "altitude": 527
        },
        {
            "time": "2023-11-03T02:56:07.000Z",
            "latitude": 35.99054371,
            "longitude": 139.186375878,
            "altitude": 527
        },
        {
            "time": "2023-11-03T02:56:09.000Z",
            "latitude": 35.990510377999996,
            "longitude": 139.18635921199999,
            "altitude": 526
        },
        {
            "time": "2023-11-03T02:56:11.000Z",
            "latitude": 35.990477046,
            "longitude": 139.186342546,
            "altitude": 526
        },
        {
            "time": "2023-11-03T02:56:15.000Z",
            "latitude": 35.990427047999994,
            "longitude": 139.18632587999997,
            "altitude": 526
        },
        {
            "time": "2023-11-03T02:56:17.000Z",
            "latitude": 35.990410382,
            "longitude": 139.186342546,
            "altitude": 527
        },
        {
            "time": "2023-11-03T02:56:21.000Z",
            "latitude": 35.990393716,
            "longitude": 139.186392544,
            "altitude": 530
        },
        {
            "time": "2023-11-03T02:56:23.000Z",
            "latitude": 35.990377050000006,
            "longitude": 139.186392544,
            "altitude": 528
        },
        {
            "time": "2023-11-03T02:56:25.000Z",
            "latitude": 35.990360384,
            "longitude": 139.18640921,
            "altitude": 529
        },
        {
            "time": "2023-11-03T02:56:27.000Z",
            "latitude": 35.990360384,
            "longitude": 139.186392544,
            "altitude": 528
        },
        {
            "time": "2023-11-03T02:56:29.000Z",
            "latitude": 35.990360384,
            "longitude": 139.186392544,
            "altitude": 528
        },
        {
            "time": "2023-11-03T02:56:31.000Z",
            "latitude": 35.990360384,
            "longitude": 139.186375878,
            "altitude": 528
        },
        {
            "time": "2023-11-03T02:56:33.000Z",
            "latitude": 35.990360384,
            "longitude": 139.186375878,
            "altitude": 529
        },
        {
            "time": "2023-11-03T02:56:35.000Z",
            "latitude": 35.990327052,
            "longitude": 139.186392544,
            "altitude": 526
        },
        {
            "time": "2023-11-03T02:56:37.000Z",
            "latitude": 35.990310386,
            "longitude": 139.186392544,
            "altitude": 525
        },
        {
            "time": "2023-11-03T02:56:39.000Z",
            "latitude": 35.990310386,
            "longitude": 139.186392544,
            "altitude": 524
        },
        {
            "time": "2023-11-03T02:56:41.000Z",
            "latitude": 35.990310386,
            "longitude": 139.186375878,
            "altitude": 522
        },
        {
            "time": "2023-11-03T02:56:43.000Z",
            "latitude": 35.990327052,
            "longitude": 139.186375878,
            "altitude": 519
        },
        {
            "time": "2023-11-03T02:56:45.000Z",
            "latitude": 35.990327052,
            "longitude": 139.186375878,
            "altitude": 519
        },
        {
            "time": "2023-11-03T02:56:49.000Z",
            "latitude": 35.990327052,
            "longitude": 139.186392544,
            "altitude": 523
        },
        {
            "time": "2023-11-03T02:56:51.000Z",
            "latitude": 35.990327052,
            "longitude": 139.186392544,
            "altitude": 525
        },
        {
            "time": "2023-11-03T02:56:53.000Z",
            "latitude": 35.990327052,
            "longitude": 139.186392544,
            "altitude": 525
        },
        {
            "time": "2023-11-03T02:56:55.000Z",
            "latitude": 35.990327052,
            "longitude": 139.186392544,
            "altitude": 524
        },
        {
            "time": "2023-11-03T02:56:57.000Z",
            "latitude": 35.990327052,
            "longitude": 139.186392544,
            "altitude": 524
        },
        {
            "time": "2023-11-03T02:56:59.000Z",
            "latitude": 35.990327052,
            "longitude": 139.186375878,
            "altitude": 523
        },
        {
            "time": "2023-11-03T02:57:03.000Z",
            "latitude": 35.990327052,
            "longitude": 139.186375878,
            "altitude": 524
        },
        {
            "time": "2023-11-03T02:57:05.000Z",
            "latitude": 35.990327052,
            "longitude": 139.18635921199999,
            "altitude": 525
        },
        {
            "time": "2023-11-03T02:57:07.000Z",
            "latitude": 35.990327052,
            "longitude": 139.186342546,
            "altitude": 525
        },
        {
            "time": "2023-11-03T02:57:09.000Z",
            "latitude": 35.990327052,
            "longitude": 139.186342546,
            "altitude": 525
        },
        {
            "time": "2023-11-03T02:57:11.000Z",
            "latitude": 35.990327052,
            "longitude": 139.186342546,
            "altitude": 525
        },
        {
            "time": "2023-11-03T02:57:13.000Z",
            "latitude": 35.990327052,
            "longitude": 139.186342546,
            "altitude": 525
        },
        {
            "time": "2023-11-03T02:57:17.000Z",
            "latitude": 35.990327052,
            "longitude": 139.18632587999997,
            "altitude": 526
        },
        {
            "time": "2023-11-03T02:57:19.000Z",
            "latitude": 35.990327052,
            "longitude": 139.18632587999997,
            "altitude": 525
        },
        {
            "time": "2023-11-03T02:57:21.000Z",
            "latitude": 35.990327052,
            "longitude": 139.186342546,
            "altitude": 524
        },
        {
            "time": "2023-11-03T02:57:23.000Z",
            "latitude": 35.990310386,
            "longitude": 139.18632587999997,
            "altitude": 524
        },
        {
            "time": "2023-11-03T02:57:25.000Z",
            "latitude": 35.990310386,
            "longitude": 139.18632587999997,
            "altitude": 524
        },
        {
            "time": "2023-11-03T02:57:27.000Z",
            "latitude": 35.990327052,
            "longitude": 139.186342546,
            "altitude": 525
        },
        {
            "time": "2023-11-03T02:57:29.000Z",
            "latitude": 35.990327052,
            "longitude": 139.18635921199999,
            "altitude": 524
        },
        {
            "time": "2023-11-03T02:57:33.000Z",
            "latitude": 35.990310386,
            "longitude": 139.186375878,
            "altitude": 522
        },
        {
            "time": "2023-11-03T02:57:35.000Z",
            "latitude": 35.990310386,
            "longitude": 139.186375878,
            "altitude": 526
        },
        {
            "time": "2023-11-03T02:57:37.000Z",
            "latitude": 35.990310386,
            "longitude": 139.186392544,
            "altitude": 527
        },
        {
            "time": "2023-11-03T02:57:39.000Z",
            "latitude": 35.990310386,
            "longitude": 139.186375878,
            "altitude": 527
        },
        {
            "time": "2023-11-03T02:57:41.000Z",
            "latitude": 35.990310386,
            "longitude": 139.186375878,
            "altitude": 526
        },
        {
            "time": "2023-11-03T02:57:45.000Z",
            "latitude": 35.990293720000004,
            "longitude": 139.186392544,
            "altitude": 525
        },
        {
            "time": "2023-11-03T02:57:47.000Z",
            "latitude": 35.990293720000004,
            "longitude": 139.186392544,
            "altitude": 525
        },
        {
            "time": "2023-11-03T02:57:49.000Z",
            "latitude": 35.990293720000004,
            "longitude": 139.186392544,
            "altitude": 525
        },
        {
            "time": "2023-11-03T02:57:51.000Z",
            "latitude": 35.990293720000004,
            "longitude": 139.186392544,
            "altitude": 525
        },
        {
            "time": "2023-11-03T02:57:55.000Z",
            "latitude": 35.990293720000004,
            "longitude": 139.186392544,
            "altitude": 525
        },
        {
            "time": "2023-11-03T02:57:57.000Z",
            "latitude": 35.990293720000004,
            "longitude": 139.186392544,
            "altitude": 525
        },
        {
            "time": "2023-11-03T02:57:59.000Z",
            "latitude": 35.990293720000004,
            "longitude": 139.186392544,
            "altitude": 525
        },
        {
            "time": "2023-11-03T02:58:01.000Z",
            "latitude": 35.990293720000004,
            "longitude": 139.186392544,
            "altitude": 525
        },
        {
            "time": "2023-11-03T02:58:03.000Z",
            "latitude": 35.990293720000004,
            "longitude": 139.186392544,
            "altitude": 524
        },
        {
            "time": "2023-11-03T02:58:05.000Z",
            "latitude": 35.990293720000004,
            "longitude": 139.186392544,
            "altitude": 524
        },
        {
            "time": "2023-11-03T02:58:07.000Z",
            "latitude": 35.990293720000004,
            "longitude": 139.186392544,
            "altitude": 524
        },
        {
            "time": "2023-11-03T02:58:09.000Z",
            "latitude": 35.990293720000004,
            "longitude": 139.186392544,
            "altitude": 525
        },
        {
            "time": "2023-11-03T02:58:11.000Z",
            "latitude": 35.990293720000004,
            "longitude": 139.186392544,
            "altitude": 525
        },
        {
            "time": "2023-11-03T02:58:15.000Z",
            "latitude": 35.990293720000004,
            "longitude": 139.186392544,
            "altitude": 525
        },
        {
            "time": "2023-11-03T02:58:17.000Z",
            "latitude": 35.990310386,
            "longitude": 139.186392544,
            "altitude": 525
        },
        {
            "time": "2023-11-03T02:58:19.000Z",
            "latitude": 35.990327052,
            "longitude": 139.186375878,
            "altitude": 526
        },
        {
            "time": "2023-11-03T02:58:21.000Z",
            "latitude": 35.990327052,
            "longitude": 139.186375878,
            "altitude": 526
        },
        {
            "time": "2023-11-03T02:58:25.000Z",
            "latitude": 35.990343718000005,
            "longitude": 139.186375878,
            "altitude": 524
        },
        {
            "time": "2023-11-03T02:58:27.000Z",
            "latitude": 35.990343718000005,
            "longitude": 139.186375878,
            "altitude": 523
        },
        {
            "time": "2023-11-03T02:58:29.000Z",
            "latitude": 35.990343718000005,
            "longitude": 139.186375878,
            "altitude": 522
        },
        {
            "time": "2023-11-03T02:58:31.000Z",
            "latitude": 35.990327052,
            "longitude": 139.186375878,
            "altitude": 521
        },
        {
            "time": "2023-11-03T02:58:35.000Z",
            "latitude": 35.990327052,
            "longitude": 139.186392544,
            "altitude": 520
        },
        {
            "time": "2023-11-03T02:58:37.000Z",
            "latitude": 35.990327052,
            "longitude": 139.186375878,
            "altitude": 521
        },
        {
            "time": "2023-11-03T02:58:39.000Z",
            "latitude": 35.990327052,
            "longitude": 139.186375878,
            "altitude": 521
        }
    ],
    "pilotname": "gengeeg50",
    "distance": "1.1 km",
    "duration": "00:10:32",
    "activity": "Paraglider",
    "area": " Komach Skyparki Paraglider School_Saitama"
}