{
    "track_points": [
        {
            "time": "2023-11-03T03:08:06.000Z",
            "latitude": 35.84013306,
            "longitude": 137.88103142399999,
            "altitude": 1314
        },
        {
            "time": "2023-11-03T03:08:08.000Z",
            "latitude": 35.84004973,
            "longitude": 137.88123141600002,
            "altitude": 1313
        },
        {
            "time": "2023-11-03T03:08:10.000Z",
            "latitude": 35.839966399999994,
            "longitude": 137.88141474200003,
            "altitude": 1312
        },
        {
            "time": "2023-11-03T03:08:12.000Z",
            "latitude": 35.839883070000006,
            "longitude": 137.881598068,
            "altitude": 1312
        },
        {
            "time": "2023-11-03T03:08:14.000Z",
            "latitude": 35.839799740000004,
            "longitude": 137.881781394,
            "altitude": 1312
        },
        {
            "time": "2023-11-03T03:08:16.000Z",
            "latitude": 35.83971641,
            "longitude": 137.88196472,
            "altitude": 1312
        },
        {
            "time": "2023-11-03T03:08:18.000Z",
            "latitude": 35.839599748,
            "longitude": 137.88216471200002,
            "altitude": 1314
        },
        {
            "time": "2023-11-03T03:08:20.000Z",
            "latitude": 35.839483085999994,
            "longitude": 137.88231470600002,
            "altitude": 1319
        },
        {
            "time": "2023-11-03T03:08:22.000Z",
            "latitude": 35.83938309,
            "longitude": 137.882431368,
            "altitude": 1321
        },
        {
            "time": "2023-11-03T03:08:24.000Z",
            "latitude": 35.839316426,
            "longitude": 137.88258136200002,
            "altitude": 1322
        },
        {
            "time": "2023-11-03T03:08:26.000Z",
            "latitude": 35.83938309,
            "longitude": 137.88273135600002,
            "altitude": 1319
        },
        {
            "time": "2023-11-03T03:08:28.000Z",
            "latitude": 35.839516417999995,
            "longitude": 137.88288135000002,
            "altitude": 1318
        },
        {
            "time": "2023-11-03T03:08:30.000Z",
            "latitude": 35.83966641199999,
            "longitude": 137.88259802800002,
            "altitude": 1317
        },
        {
            "time": "2023-11-03T03:08:32.000Z",
            "latitude": 35.839549749999996,
            "longitude": 137.882414702,
            "altitude": 1322
        },
        {
            "time": "2023-11-03T03:08:34.000Z",
            "latitude": 35.839416422,
            "longitude": 137.882264708,
            "altitude": 1327
        },
        {
            "time": "2023-11-03T03:08:36.000Z",
            "latitude": 35.839366424,
            "longitude": 137.882114714,
            "altitude": 1324
        },
        {
            "time": "2023-11-03T03:08:38.000Z",
            "latitude": 35.839233096,
            "longitude": 137.88199805200003,
            "altitude": 1322
        },
        {
            "time": "2023-11-03T03:08:40.000Z",
            "latitude": 35.83904977,
            "longitude": 137.88191472199998,
            "altitude": 1320
        },
        {
            "time": "2023-11-03T03:08:42.000Z",
            "latitude": 35.838866444000004,
            "longitude": 137.881981386,
            "altitude": 1317
        },
        {
            "time": "2023-11-03T03:08:44.000Z",
            "latitude": 35.83871645,
            "longitude": 137.882064716,
            "altitude": 1311
        },
        {
            "time": "2023-11-03T03:08:46.000Z",
            "latitude": 35.838583121999996,
            "longitude": 137.88218137799998,
            "altitude": 1308
        },
        {
            "time": "2023-11-03T03:08:48.000Z",
            "latitude": 35.83863312,
            "longitude": 137.8824647,
            "altitude": 1305
        },
        {
            "time": "2023-11-03T03:08:50.000Z",
            "latitude": 35.838699784,
            "longitude": 137.88263135999998,
            "altitude": 1302
        },
        {
            "time": "2023-11-03T03:08:52.000Z",
            "latitude": 35.838783114,
            "longitude": 137.882764688,
            "altitude": 1300
        },
        {
            "time": "2023-11-03T03:08:54.000Z",
            "latitude": 35.83894977400001,
            "longitude": 137.882814686,
            "altitude": 1293
        },
        {
            "time": "2023-11-03T03:08:56.000Z",
            "latitude": 35.839116434,
            "longitude": 137.88283135199998,
            "altitude": 1291
        },
        {
            "time": "2023-11-03T03:08:58.000Z",
            "latitude": 35.839283094,
            "longitude": 137.882864684,
            "altitude": 1292
        },
        {
            "time": "2023-11-03T03:09:00.000Z",
            "latitude": 35.83938309,
            "longitude": 137.88291468200003,
            "altitude": 1291
        },
        {
            "time": "2023-11-03T03:09:02.000Z",
            "latitude": 35.839516417999995,
            "longitude": 137.883014678,
            "altitude": 1290
        },
        {
            "time": "2023-11-03T03:09:04.000Z",
            "latitude": 35.83963308,
            "longitude": 137.883148006,
            "altitude": 1289
        },
        {
            "time": "2023-11-03T03:09:06.000Z",
            "latitude": 35.839449754,
            "longitude": 137.883431328,
            "altitude": 1286
        },
        {
            "time": "2023-11-03T03:09:08.000Z",
            "latitude": 35.839266428,
            "longitude": 137.88341466199998,
            "altitude": 1289
        },
        {
            "time": "2023-11-03T03:09:10.000Z",
            "latitude": 35.839099768000004,
            "longitude": 137.88331466600002,
            "altitude": 1292
        },
        {
            "time": "2023-11-03T03:09:12.000Z",
            "latitude": 35.83904977,
            "longitude": 137.88316467200002,
            "altitude": 1289
        },
        {
            "time": "2023-11-03T03:09:14.000Z",
            "latitude": 35.839066435999996,
            "longitude": 137.88293134799997,
            "altitude": 1284
        },
        {
            "time": "2023-11-03T03:09:16.000Z",
            "latitude": 35.839133100000005,
            "longitude": 137.88273135600002,
            "altitude": 1284
        },
        {
            "time": "2023-11-03T03:09:18.000Z",
            "latitude": 35.839299759999996,
            "longitude": 137.88268135799999,
            "altitude": 1286
        },
        {
            "time": "2023-11-03T03:09:20.000Z",
            "latitude": 35.83946642,
            "longitude": 137.88268135799999,
            "altitude": 1290
        },
        {
            "time": "2023-11-03T03:09:22.000Z",
            "latitude": 35.83963308,
            "longitude": 137.88273135600002,
            "altitude": 1291
        },
        {
            "time": "2023-11-03T03:09:24.000Z",
            "latitude": 35.839733076,
            "longitude": 137.882864684,
            "altitude": 1291
        },
        {
            "time": "2023-11-03T03:09:26.000Z",
            "latitude": 35.839849738,
            "longitude": 137.883014678,
            "altitude": 1286
        },
        {
            "time": "2023-11-03T03:09:28.000Z",
            "latitude": 35.839983066,
            "longitude": 137.88316467200002,
            "altitude": 1282
        },
        {
            "time": "2023-11-03T03:09:30.000Z",
            "latitude": 35.84013306,
            "longitude": 137.883281334,
            "altitude": 1279
        },
        {
            "time": "2023-11-03T03:09:32.000Z",
            "latitude": 35.840266387999996,
            "longitude": 137.883347998,
            "altitude": 1275
        },
        {
            "time": "2023-11-03T03:09:34.000Z",
            "latitude": 35.84038305,
            "longitude": 137.88339799599999,
            "altitude": 1274
        },
        {
            "time": "2023-11-03T03:09:36.000Z",
            "latitude": 35.840549710000005,
            "longitude": 137.883431328,
            "altitude": 1268
        },
        {
            "time": "2023-11-03T03:09:38.000Z",
            "latitude": 35.840699704,
            "longitude": 137.88346466000002,
            "altitude": 1268
        },
        {
            "time": "2023-11-03T03:09:40.000Z",
            "latitude": 35.840866364,
            "longitude": 137.88346466000002,
            "altitude": 1267
        },
        {
            "time": "2023-11-03T03:09:42.000Z",
            "latitude": 35.84104969,
            "longitude": 137.883531324,
            "altitude": 1262
        },
        {
            "time": "2023-11-03T03:09:44.000Z",
            "latitude": 35.841166352,
            "longitude": 137.883614654,
            "altitude": 1262
        },
        {
            "time": "2023-11-03T03:09:46.000Z",
            "latitude": 35.841283014,
            "longitude": 137.883681318,
            "altitude": 1261
        },
        {
            "time": "2023-11-03T03:09:48.000Z",
            "latitude": 35.841433008,
            "longitude": 137.883747982,
            "altitude": 1259
        },
        {
            "time": "2023-11-03T03:09:50.000Z",
            "latitude": 35.84156633599999,
            "longitude": 137.88384797799998,
            "altitude": 1258
        },
        {
            "time": "2023-11-03T03:09:52.000Z",
            "latitude": 35.841699664000004,
            "longitude": 137.88398130599998,
            "altitude": 1260
        },
        {
            "time": "2023-11-03T03:09:54.000Z",
            "latitude": 35.841849658,
            "longitude": 137.88409796800002,
            "altitude": 1266
        },
        {
            "time": "2023-11-03T03:09:56.000Z",
            "latitude": 35.841966320000004,
            "longitude": 137.88423129600002,
            "altitude": 1269
        },
        {
            "time": "2023-11-03T03:09:58.000Z",
            "latitude": 35.842099648,
            "longitude": 137.884314626,
            "altitude": 1268
        },
        {
            "time": "2023-11-03T03:10:00.000Z",
            "latitude": 35.842249642,
            "longitude": 137.884364624,
            "altitude": 1266
        },
        {
            "time": "2023-11-03T03:10:02.000Z",
            "latitude": 35.84238297,
            "longitude": 137.884447954,
            "altitude": 1264
        },
        {
            "time": "2023-11-03T03:10:04.000Z",
            "latitude": 35.84253296400001,
            "longitude": 137.884481286,
            "altitude": 1261
        },
        {
            "time": "2023-11-03T03:10:06.000Z",
            "latitude": 35.842682958,
            "longitude": 137.88453128400002,
            "altitude": 1258
        },
        {
            "time": "2023-11-03T03:10:08.000Z",
            "latitude": 35.842849618,
            "longitude": 137.88454795,
            "altitude": 1254
        },
        {
            "time": "2023-11-03T03:10:10.000Z",
            "latitude": 35.84298294599999,
            "longitude": 137.884597948,
            "altitude": 1254
        },
        {
            "time": "2023-11-03T03:10:12.000Z",
            "latitude": 35.84313294,
            "longitude": 137.88471460999997,
            "altitude": 1250
        },
        {
            "time": "2023-11-03T03:10:14.000Z",
            "latitude": 35.843266268,
            "longitude": 137.88481460600002,
            "altitude": 1250
        },
        {
            "time": "2023-11-03T03:10:16.000Z",
            "latitude": 35.843399596,
            "longitude": 137.88491460199998,
            "altitude": 1250
        },
        {
            "time": "2023-11-03T03:10:18.000Z",
            "latitude": 35.843532924,
            "longitude": 137.88501459799997,
            "altitude": 1248
        },
        {
            "time": "2023-11-03T03:10:20.000Z",
            "latitude": 35.843666252,
            "longitude": 137.88513126,
            "altitude": 1246
        },
        {
            "time": "2023-11-03T03:10:22.000Z",
            "latitude": 35.843782914,
            "longitude": 137.88524792200002,
            "altitude": 1246
        },
        {
            "time": "2023-11-03T03:10:24.000Z",
            "latitude": 35.843866244000004,
            "longitude": 137.885431248,
            "altitude": 1248
        },
        {
            "time": "2023-11-03T03:10:26.000Z",
            "latitude": 35.843932908,
            "longitude": 137.885614574,
            "altitude": 1246
        },
        {
            "time": "2023-11-03T03:10:28.000Z",
            "latitude": 35.843999571999994,
            "longitude": 137.8857979,
            "altitude": 1246
        },
        {
            "time": "2023-11-03T03:10:30.000Z",
            "latitude": 35.843982906,
            "longitude": 137.885981226,
            "altitude": 1243
        },
        {
            "time": "2023-11-03T03:10:32.000Z",
            "latitude": 35.844016238,
            "longitude": 137.88618121800002,
            "altitude": 1241
        },
        {
            "time": "2023-11-03T03:10:34.000Z",
            "latitude": 35.844016238,
            "longitude": 137.886397876,
            "altitude": 1243
        },
        {
            "time": "2023-11-03T03:10:36.000Z",
            "latitude": 35.84404957,
            "longitude": 137.886597868,
            "altitude": 1243
        },
        {
            "time": "2023-11-03T03:10:38.000Z",
            "latitude": 35.844066235999996,
            "longitude": 137.88676452800001,
            "altitude": 1245
        },
        {
            "time": "2023-11-03T03:10:40.000Z",
            "latitude": 35.844032903999995,
            "longitude": 137.886914522,
            "altitude": 1247
        },
        {
            "time": "2023-11-03T03:10:42.000Z",
            "latitude": 35.844016238,
            "longitude": 137.887181178,
            "altitude": 1245
        },
        {
            "time": "2023-11-03T03:10:44.000Z",
            "latitude": 35.843982906,
            "longitude": 137.887364504,
            "altitude": 1247
        },
        {
            "time": "2023-11-03T03:10:46.000Z",
            "latitude": 35.843982906,
            "longitude": 137.88758116199998,
            "altitude": 1246
        },
        {
            "time": "2023-11-03T03:10:48.000Z",
            "latitude": 35.84388291,
            "longitude": 137.88768115800002,
            "altitude": 1246
        },
        {
            "time": "2023-11-03T03:10:50.000Z",
            "latitude": 35.843699584,
            "longitude": 137.88768115800002,
            "altitude": 1245
        },
        {
            "time": "2023-11-03T03:10:52.000Z",
            "latitude": 35.843516258,
            "longitude": 137.887597828,
            "altitude": 1245
        },
        {
            "time": "2023-11-03T03:10:54.000Z",
            "latitude": 35.843532924,
            "longitude": 137.887364504,
            "altitude": 1244
        },
        {
            "time": "2023-11-03T03:10:56.000Z",
            "latitude": 35.843566256,
            "longitude": 137.887164512,
            "altitude": 1242
        },
        {
            "time": "2023-11-03T03:10:58.000Z",
            "latitude": 35.843649586000005,
            "longitude": 137.88699785199998,
            "altitude": 1240
        },
        {
            "time": "2023-11-03T03:11:00.000Z",
            "latitude": 35.843832912,
            "longitude": 137.88694785400003,
            "altitude": 1238
        },
        {
            "time": "2023-11-03T03:11:02.000Z",
            "latitude": 35.843982906,
            "longitude": 137.88699785199998,
            "altitude": 1239
        },
        {
            "time": "2023-11-03T03:11:04.000Z",
            "latitude": 35.844132900000005,
            "longitude": 137.887064516,
            "altitude": 1241
        },
        {
            "time": "2023-11-03T03:11:06.000Z",
            "latitude": 35.844282894,
            "longitude": 137.88721451,
            "altitude": 1238
        },
        {
            "time": "2023-11-03T03:11:08.000Z",
            "latitude": 35.84446622,
            "longitude": 137.887314506,
            "altitude": 1236
        },
        {
            "time": "2023-11-03T03:11:10.000Z",
            "latitude": 35.844616214000006,
            "longitude": 137.88743116799998,
            "altitude": 1234
        },
        {
            "time": "2023-11-03T03:11:12.000Z",
            "latitude": 35.844766208,
            "longitude": 137.887597828,
            "altitude": 1232
        },
        {
            "time": "2023-11-03T03:11:14.000Z",
            "latitude": 35.844899536,
            "longitude": 137.887764488,
            "altitude": 1229
        },
        {
            "time": "2023-11-03T03:11:16.000Z",
            "latitude": 35.845016198,
            "longitude": 137.88788115,
            "altitude": 1230
        },
        {
            "time": "2023-11-03T03:11:18.000Z",
            "latitude": 35.84514952599999,
            "longitude": 137.888064476,
            "altitude": 1229
        },
        {
            "time": "2023-11-03T03:11:20.000Z",
            "latitude": 35.845232855999996,
            "longitude": 137.888197804,
            "altitude": 1227
        },
        {
            "time": "2023-11-03T03:11:22.000Z",
            "latitude": 35.84533285199999,
            "longitude": 137.888331132,
            "altitude": 1223
        },
        {
            "time": "2023-11-03T03:11:24.000Z",
            "latitude": 35.84546618,
            "longitude": 137.888531124,
            "altitude": 1218
        },
        {
            "time": "2023-11-03T03:11:26.000Z",
            "latitude": 35.845599508,
            "longitude": 137.888664452,
            "altitude": 1216
        },
        {
            "time": "2023-11-03T03:11:28.000Z",
            "latitude": 35.845732836,
            "longitude": 137.88871445,
            "altitude": 1215
        },
        {
            "time": "2023-11-03T03:11:30.000Z",
            "latitude": 35.845916162,
            "longitude": 137.88874778199997,
            "altitude": 1213
        },
        {
            "time": "2023-11-03T03:11:32.000Z",
            "latitude": 35.846099488,
            "longitude": 137.88869778400002,
            "altitude": 1212
        },
        {
            "time": "2023-11-03T03:11:34.000Z",
            "latitude": 35.846249482000005,
            "longitude": 137.888681118,
            "altitude": 1213
        },
        {
            "time": "2023-11-03T03:11:36.000Z",
            "latitude": 35.846382809999994,
            "longitude": 137.88858112200003,
            "altitude": 1209
        },
        {
            "time": "2023-11-03T03:11:38.000Z",
            "latitude": 35.84654947,
            "longitude": 137.888481126,
            "altitude": 1208
        },
        {
            "time": "2023-11-03T03:11:40.000Z",
            "latitude": 35.846682797999996,
            "longitude": 137.888364464,
            "altitude": 1207
        },
        {
            "time": "2023-11-03T03:11:42.000Z",
            "latitude": 35.846849458,
            "longitude": 137.88821447,
            "altitude": 1203
        },
        {
            "time": "2023-11-03T03:11:44.000Z",
            "latitude": 35.846999452000006,
            "longitude": 137.888097808,
            "altitude": 1202
        },
        {
            "time": "2023-11-03T03:11:46.000Z",
            "latitude": 35.847166112,
            "longitude": 137.88799781199998,
            "altitude": 1202
        },
        {
            "time": "2023-11-03T03:11:48.000Z",
            "latitude": 35.84729944,
            "longitude": 137.88796448000002,
            "altitude": 1199
        },
        {
            "time": "2023-11-03T03:11:50.000Z",
            "latitude": 35.8474661,
            "longitude": 137.887897816,
            "altitude": 1195
        },
        {
            "time": "2023-11-03T03:11:52.000Z",
            "latitude": 35.84763276,
            "longitude": 137.88786448399998,
            "altitude": 1193
        },
        {
            "time": "2023-11-03T03:11:54.000Z",
            "latitude": 35.847782754,
            "longitude": 137.88786448399998,
            "altitude": 1189
        },
        {
            "time": "2023-11-03T03:11:56.000Z",
            "latitude": 35.847932748000005,
            "longitude": 137.88783115200002,
            "altitude": 1186
        },
        {
            "time": "2023-11-03T03:11:58.000Z",
            "latitude": 35.848082742,
            "longitude": 137.887781154,
            "altitude": 1184
        },
        {
            "time": "2023-11-03T03:12:00.000Z",
            "latitude": 35.848232736,
            "longitude": 137.887781154,
            "altitude": 1180
        },
        {
            "time": "2023-11-03T03:12:02.000Z",
            "latitude": 35.848382730000004,
            "longitude": 137.887747822,
            "altitude": 1179
        },
        {
            "time": "2023-11-03T03:12:04.000Z",
            "latitude": 35.848516058,
            "longitude": 137.88781448600002,
            "altitude": 1176
        },
        {
            "time": "2023-11-03T03:12:06.000Z",
            "latitude": 35.848682718000006,
            "longitude": 137.88783115200002,
            "altitude": 1172
        },
        {
            "time": "2023-11-03T03:12:08.000Z",
            "latitude": 35.848849378,
            "longitude": 137.88783115200002,
            "altitude": 1173
        },
        {
            "time": "2023-11-03T03:12:10.000Z",
            "latitude": 35.848999371999994,
            "longitude": 137.887781154,
            "altitude": 1175
        },
        {
            "time": "2023-11-03T03:12:12.000Z",
            "latitude": 35.849149366,
            "longitude": 137.88768115800002,
            "altitude": 1171
        },
        {
            "time": "2023-11-03T03:12:14.000Z",
            "latitude": 35.849299359999996,
            "longitude": 137.887731156,
            "altitude": 1167
        },
        {
            "time": "2023-11-03T03:12:16.000Z",
            "latitude": 35.84946602,
            "longitude": 137.887781154,
            "altitude": 1165
        },
        {
            "time": "2023-11-03T03:12:18.000Z",
            "latitude": 35.849566016,
            "longitude": 137.887897816,
            "altitude": 1166
        },
        {
            "time": "2023-11-03T03:12:20.000Z",
            "latitude": 35.849699343999994,
            "longitude": 137.88799781199998,
            "altitude": 1164
        },
        {
            "time": "2023-11-03T03:12:22.000Z",
            "latitude": 35.849832672000005,
            "longitude": 137.88824780200002,
            "altitude": 1162
        },
        {
            "time": "2023-11-03T03:12:24.000Z",
            "latitude": 35.849932668,
            "longitude": 137.88834779799998,
            "altitude": 1161
        },
        {
            "time": "2023-11-03T03:12:26.000Z",
            "latitude": 35.850032664000004,
            "longitude": 137.888481126,
            "altitude": 1160
        },
        {
            "time": "2023-11-03T03:12:28.000Z",
            "latitude": 35.850199324,
            "longitude": 137.888614454,
            "altitude": 1157
        },
        {
            "time": "2023-11-03T03:12:30.000Z",
            "latitude": 35.85029932,
            "longitude": 137.888664452,
            "altitude": 1156
        },
        {
            "time": "2023-11-03T03:12:32.000Z",
            "latitude": 35.850432648,
            "longitude": 137.888681118,
            "altitude": 1156
        },
        {
            "time": "2023-11-03T03:12:34.000Z",
            "latitude": 35.850565976,
            "longitude": 137.888764448,
            "altitude": 1150
        },
        {
            "time": "2023-11-03T03:12:36.000Z",
            "latitude": 35.850749302,
            "longitude": 137.88879778,
            "altitude": 1149
        },
        {
            "time": "2023-11-03T03:12:38.000Z",
            "latitude": 35.85088263,
            "longitude": 137.88883111200002,
            "altitude": 1148
        },
        {
            "time": "2023-11-03T03:12:40.000Z",
            "latitude": 35.850999292000004,
            "longitude": 137.888864444,
            "altitude": 1143
        },
        {
            "time": "2023-11-03T03:12:42.000Z",
            "latitude": 35.85113262,
            "longitude": 137.888914442,
            "altitude": 1140
        },
        {
            "time": "2023-11-03T03:12:44.000Z",
            "latitude": 35.851265948,
            "longitude": 137.88904777,
            "altitude": 1138
        },
        {
            "time": "2023-11-03T03:12:46.000Z",
            "latitude": 35.851315946,
            "longitude": 137.889197764,
            "altitude": 1140
        },
        {
            "time": "2023-11-03T03:12:48.000Z",
            "latitude": 35.851415941999996,
            "longitude": 137.889281094,
            "altitude": 1137
        },
        {
            "time": "2023-11-03T03:12:50.000Z",
            "latitude": 35.851499272,
            "longitude": 137.889397756,
            "altitude": 1133
        },
        {
            "time": "2023-11-03T03:12:52.000Z",
            "latitude": 35.85154927,
            "longitude": 137.889597748,
            "altitude": 1127
        },
        {
            "time": "2023-11-03T03:12:54.000Z",
            "latitude": 35.85159926800001,
            "longitude": 137.88976440800002,
            "altitude": 1129
        },
        {
            "time": "2023-11-03T03:12:56.000Z",
            "latitude": 35.851615934,
            "longitude": 137.889931068,
            "altitude": 1133
        },
        {
            "time": "2023-11-03T03:12:58.000Z",
            "latitude": 35.851649265999995,
            "longitude": 137.89009772799997,
            "altitude": 1135
        },
        {
            "time": "2023-11-03T03:13:00.000Z",
            "latitude": 35.851699264000004,
            "longitude": 137.890264388,
            "altitude": 1134
        },
        {
            "time": "2023-11-03T03:13:02.000Z",
            "latitude": 35.85174926199999,
            "longitude": 137.89048104600002,
            "altitude": 1133
        },
        {
            "time": "2023-11-03T03:13:04.000Z",
            "latitude": 35.851732596,
            "longitude": 137.89066437200003,
            "altitude": 1132
        },
        {
            "time": "2023-11-03T03:13:06.000Z",
            "latitude": 35.85174926199999,
            "longitude": 137.89086436399998,
            "altitude": 1132
        },
        {
            "time": "2023-11-03T03:13:08.000Z",
            "latitude": 35.85174926199999,
            "longitude": 137.891031024,
            "altitude": 1130
        },
        {
            "time": "2023-11-03T03:13:10.000Z",
            "latitude": 35.85179926,
            "longitude": 137.891181018,
            "altitude": 1125
        },
        {
            "time": "2023-11-03T03:13:12.000Z",
            "latitude": 35.851815926,
            "longitude": 137.891364344,
            "altitude": 1120
        },
        {
            "time": "2023-11-03T03:13:14.000Z",
            "latitude": 35.851849258,
            "longitude": 137.89154767000002,
            "altitude": 1120
        },
        {
            "time": "2023-11-03T03:13:16.000Z",
            "latitude": 35.851865923999995,
            "longitude": 137.89173099599998,
            "altitude": 1118
        },
        {
            "time": "2023-11-03T03:13:18.000Z",
            "latitude": 35.851865923999995,
            "longitude": 137.89193098799998,
            "altitude": 1116
        },
        {
            "time": "2023-11-03T03:13:20.000Z",
            "latitude": 35.851832591999994,
            "longitude": 137.892114314,
            "altitude": 1118
        },
        {
            "time": "2023-11-03T03:13:22.000Z",
            "latitude": 35.85179926,
            "longitude": 137.89229764,
            "altitude": 1121
        },
        {
            "time": "2023-11-03T03:13:24.000Z",
            "latitude": 35.851732596,
            "longitude": 137.89246430000003,
            "altitude": 1126
        },
        {
            "time": "2023-11-03T03:13:26.000Z",
            "latitude": 35.851682598,
            "longitude": 137.89261429400003,
            "altitude": 1131
        },
        {
            "time": "2023-11-03T03:13:28.000Z",
            "latitude": 35.85156593599999,
            "longitude": 137.892814286,
            "altitude": 1128
        },
        {
            "time": "2023-11-03T03:13:30.000Z",
            "latitude": 35.85146594,
            "longitude": 137.892997612,
            "altitude": 1127
        },
        {
            "time": "2023-11-03T03:13:32.000Z",
            "latitude": 35.851349278,
            "longitude": 137.893147606,
            "altitude": 1125
        },
        {
            "time": "2023-11-03T03:13:34.000Z",
            "latitude": 35.851182618,
            "longitude": 137.89324760199997,
            "altitude": 1120
        },
        {
            "time": "2023-11-03T03:13:36.000Z",
            "latitude": 35.850999292000004,
            "longitude": 137.89319760400002,
            "altitude": 1117
        },
        {
            "time": "2023-11-03T03:13:38.000Z",
            "latitude": 35.850832632,
            "longitude": 137.89306427600002,
            "altitude": 1115
        },
        {
            "time": "2023-11-03T03:13:40.000Z",
            "latitude": 35.850699304,
            "longitude": 137.89291428200002,
            "altitude": 1110
        },
        {
            "time": "2023-11-03T03:13:42.000Z",
            "latitude": 35.850582642000006,
            "longitude": 137.89271429000001,
            "altitude": 1109
        },
        {
            "time": "2023-11-03T03:13:44.000Z",
            "latitude": 35.850532644,
            "longitude": 137.892480966,
            "altitude": 1110
        },
        {
            "time": "2023-11-03T03:13:46.000Z",
            "latitude": 35.850482645999996,
            "longitude": 137.892264308,
            "altitude": 1114
        },
        {
            "time": "2023-11-03T03:13:48.000Z",
            "latitude": 35.850482645999996,
            "longitude": 137.892064316,
            "altitude": 1112
        },
        {
            "time": "2023-11-03T03:13:50.000Z",
            "latitude": 35.850482645999996,
            "longitude": 137.891864324,
            "altitude": 1109
        },
        {
            "time": "2023-11-03T03:13:52.000Z",
            "latitude": 35.85066597200001,
            "longitude": 137.89173099599998,
            "altitude": 1107
        },
        {
            "time": "2023-11-03T03:13:54.000Z",
            "latitude": 35.85081596599999,
            "longitude": 137.89171433,
            "altitude": 1107
        },
        {
            "time": "2023-11-03T03:13:56.000Z",
            "latitude": 35.850949294,
            "longitude": 137.89171433,
            "altitude": 1105
        },
        {
            "time": "2023-11-03T03:13:58.000Z",
            "latitude": 35.85113262,
            "longitude": 137.89179766,
            "altitude": 1101
        },
        {
            "time": "2023-11-03T03:14:00.000Z",
            "latitude": 35.851249282000005,
            "longitude": 137.891914322,
            "altitude": 1101
        },
        {
            "time": "2023-11-03T03:14:02.000Z",
            "latitude": 35.85133261200001,
            "longitude": 137.89204765,
            "altitude": 1102
        },
        {
            "time": "2023-11-03T03:14:04.000Z",
            "latitude": 35.851415941999996,
            "longitude": 137.892230976,
            "altitude": 1100
        },
        {
            "time": "2023-11-03T03:14:06.000Z",
            "latitude": 35.851399276,
            "longitude": 137.892447634,
            "altitude": 1103
        },
        {
            "time": "2023-11-03T03:14:08.000Z",
            "latitude": 35.85133261200001,
            "longitude": 137.89263096,
            "altitude": 1105
        },
        {
            "time": "2023-11-03T03:14:10.000Z",
            "latitude": 35.851115953999994,
            "longitude": 137.89256429600002,
            "altitude": 1104
        },
        {
            "time": "2023-11-03T03:14:12.000Z",
            "latitude": 35.850999292000004,
            "longitude": 137.892397636,
            "altitude": 1105
        },
        {
            "time": "2023-11-03T03:14:14.000Z",
            "latitude": 35.850949294,
            "longitude": 137.89218097799997,
            "altitude": 1106
        },
        {
            "time": "2023-11-03T03:14:16.000Z",
            "latitude": 35.85104929,
            "longitude": 137.89198098600002,
            "altitude": 1106
        },
        {
            "time": "2023-11-03T03:14:18.000Z",
            "latitude": 35.851199283999996,
            "longitude": 137.892014318,
            "altitude": 1104
        },
        {
            "time": "2023-11-03T03:14:20.000Z",
            "latitude": 35.851365944,
            "longitude": 137.892114314,
            "altitude": 1105
        },
        {
            "time": "2023-11-03T03:14:22.000Z",
            "latitude": 35.85146594,
            "longitude": 137.89221430999999,
            "altitude": 1102
        },
        {
            "time": "2023-11-03T03:14:24.000Z",
            "latitude": 35.851499272,
            "longitude": 137.892430968,
            "altitude": 1100
        },
        {
            "time": "2023-11-03T03:14:26.000Z",
            "latitude": 35.851532604,
            "longitude": 137.89266429199998,
            "altitude": 1099
        },
        {
            "time": "2023-11-03T03:14:28.000Z",
            "latitude": 35.851365944,
            "longitude": 137.892814286,
            "altitude": 1095
        },
        {
            "time": "2023-11-03T03:14:30.000Z",
            "latitude": 35.851215950000004,
            "longitude": 137.892864284,
            "altitude": 1095
        },
        {
            "time": "2023-11-03T03:14:32.000Z",
            "latitude": 35.85104929,
            "longitude": 137.892864284,
            "altitude": 1093
        },
        {
            "time": "2023-11-03T03:14:34.000Z",
            "latitude": 35.850932627999995,
            "longitude": 137.892680958,
            "altitude": 1095
        },
        {
            "time": "2023-11-03T03:14:36.000Z",
            "latitude": 35.85084929800001,
            "longitude": 137.892480966,
            "altitude": 1094
        },
        {
            "time": "2023-11-03T03:14:38.000Z",
            "latitude": 35.85084929800001,
            "longitude": 137.89229764,
            "altitude": 1093
        },
        {
            "time": "2023-11-03T03:14:40.000Z",
            "latitude": 35.850915962,
            "longitude": 137.89208098199998,
            "altitude": 1094
        },
        {
            "time": "2023-11-03T03:14:42.000Z",
            "latitude": 35.85104929,
            "longitude": 137.89198098600002,
            "altitude": 1094
        },
        {
            "time": "2023-11-03T03:14:44.000Z",
            "latitude": 35.851232616,
            "longitude": 137.89196432,
            "altitude": 1093
        },
        {
            "time": "2023-11-03T03:14:46.000Z",
            "latitude": 35.851382609999995,
            "longitude": 137.892097648,
            "altitude": 1088
        },
        {
            "time": "2023-11-03T03:14:48.000Z",
            "latitude": 35.851415941999996,
            "longitude": 137.89229764,
            "altitude": 1087
        },
        {
            "time": "2023-11-03T03:14:50.000Z",
            "latitude": 35.851432608,
            "longitude": 137.89251429799998,
            "altitude": 1086
        },
        {
            "time": "2023-11-03T03:14:52.000Z",
            "latitude": 35.851349278,
            "longitude": 137.89263096,
            "altitude": 1088
        },
        {
            "time": "2023-11-03T03:14:54.000Z",
            "latitude": 35.851215950000004,
            "longitude": 137.89271429000001,
            "altitude": 1086
        },
        {
            "time": "2023-11-03T03:14:56.000Z",
            "latitude": 35.85104929,
            "longitude": 137.89279761999998,
            "altitude": 1085
        },
        {
            "time": "2023-11-03T03:14:58.000Z",
            "latitude": 35.85088263,
            "longitude": 137.89263096,
            "altitude": 1086
        },
        {
            "time": "2023-11-03T03:15:00.000Z",
            "latitude": 35.8507993,
            "longitude": 137.89241430200002,
            "altitude": 1084
        },
        {
            "time": "2023-11-03T03:15:02.000Z",
            "latitude": 35.850782634,
            "longitude": 137.89216431200003,
            "altitude": 1081
        },
        {
            "time": "2023-11-03T03:15:04.000Z",
            "latitude": 35.850949294,
            "longitude": 137.89196432,
            "altitude": 1081
        },
        {
            "time": "2023-11-03T03:15:06.000Z",
            "latitude": 35.851032624000005,
            "longitude": 137.89183099200002,
            "altitude": 1079
        },
        {
            "time": "2023-11-03T03:15:08.000Z",
            "latitude": 35.85113262,
            "longitude": 137.89171433,
            "altitude": 1079
        },
        {
            "time": "2023-11-03T03:15:10.000Z",
            "latitude": 35.851349278,
            "longitude": 137.891664332,
            "altitude": 1078
        },
        {
            "time": "2023-11-03T03:15:12.000Z",
            "latitude": 35.851499272,
            "longitude": 137.891647666,
            "altitude": 1080
        },
        {
            "time": "2023-11-03T03:15:14.000Z",
            "latitude": 35.8516326,
            "longitude": 137.891664332,
            "altitude": 1078
        },
        {
            "time": "2023-11-03T03:15:16.000Z",
            "latitude": 35.85174926199999,
            "longitude": 137.89171433,
            "altitude": 1076
        },
        {
            "time": "2023-11-03T03:15:18.000Z",
            "latitude": 35.851915922,
            "longitude": 137.89174766199997,
            "altitude": 1075
        },
        {
            "time": "2023-11-03T03:15:20.000Z",
            "latitude": 35.85204924999999,
            "longitude": 137.89174766199997,
            "altitude": 1072
        },
        {
            "time": "2023-11-03T03:15:22.000Z",
            "latitude": 35.852165912,
            "longitude": 137.89184765800002,
            "altitude": 1070
        },
        {
            "time": "2023-11-03T03:15:24.000Z",
            "latitude": 35.85226590800001,
            "longitude": 137.892014318,
            "altitude": 1067
        },
        {
            "time": "2023-11-03T03:15:26.000Z",
            "latitude": 35.852332572,
            "longitude": 137.89216431200003,
            "altitude": 1065
        },
        {
            "time": "2023-11-03T03:15:28.000Z",
            "latitude": 35.852349237999995,
            "longitude": 137.892347638,
            "altitude": 1062
        },
        {
            "time": "2023-11-03T03:15:30.000Z",
            "latitude": 35.852382569999996,
            "longitude": 137.89251429799998,
            "altitude": 1061
        },
        {
            "time": "2023-11-03T03:15:32.000Z",
            "latitude": 35.852349237999995,
            "longitude": 137.89266429199998,
            "altitude": 1059
        },
        {
            "time": "2023-11-03T03:15:34.000Z",
            "latitude": 35.852282574,
            "longitude": 137.892830952,
            "altitude": 1061
        },
        {
            "time": "2023-11-03T03:15:36.000Z",
            "latitude": 35.852182578000004,
            "longitude": 137.893014278,
            "altitude": 1057
        },
        {
            "time": "2023-11-03T03:15:38.000Z",
            "latitude": 35.852032584,
            "longitude": 137.893114274,
            "altitude": 1056
        },
        {
            "time": "2023-11-03T03:15:40.000Z",
            "latitude": 35.851865923999995,
            "longitude": 137.893147606,
            "altitude": 1052
        },
        {
            "time": "2023-11-03T03:15:42.000Z",
            "latitude": 35.851699264000004,
            "longitude": 137.893014278,
            "altitude": 1048
        },
        {
            "time": "2023-11-03T03:15:44.000Z",
            "latitude": 35.851532604,
            "longitude": 137.892847618,
            "altitude": 1045
        },
        {
            "time": "2023-11-03T03:15:46.000Z",
            "latitude": 35.851615934,
            "longitude": 137.89256429600002,
            "altitude": 1039
        },
        {
            "time": "2023-11-03T03:15:48.000Z",
            "latitude": 35.851732596,
            "longitude": 137.89246430000003,
            "altitude": 1036
        },
        {
            "time": "2023-11-03T03:15:50.000Z",
            "latitude": 35.85188259,
            "longitude": 137.892430968,
            "altitude": 1034
        },
        {
            "time": "2023-11-03T03:15:52.000Z",
            "latitude": 35.851999252000006,
            "longitude": 137.892580962,
            "altitude": 1032
        },
        {
            "time": "2023-11-03T03:15:54.000Z",
            "latitude": 35.852132579999996,
            "longitude": 137.89266429199998,
            "altitude": 1028
        },
        {
            "time": "2023-11-03T03:15:56.000Z",
            "latitude": 35.852249242,
            "longitude": 137.892697624,
            "altitude": 1027
        },
        {
            "time": "2023-11-03T03:15:58.000Z",
            "latitude": 35.852282574,
            "longitude": 137.892864284,
            "altitude": 1024
        },
        {
            "time": "2023-11-03T03:16:00.000Z",
            "latitude": 35.852282574,
            "longitude": 137.89304761000002,
            "altitude": 1021
        },
        {
            "time": "2023-11-03T03:16:02.000Z",
            "latitude": 35.852282574,
            "longitude": 137.89321427000002,
            "altitude": 1020
        },
        {
            "time": "2023-11-03T03:16:04.000Z",
            "latitude": 35.852332572,
            "longitude": 137.893430928,
            "altitude": 1016
        },
        {
            "time": "2023-11-03T03:16:06.000Z",
            "latitude": 35.852365904,
            "longitude": 137.89363092000002,
            "altitude": 1015
        },
        {
            "time": "2023-11-03T03:16:08.000Z",
            "latitude": 35.852382569999996,
            "longitude": 137.89379758,
            "altitude": 1013
        },
        {
            "time": "2023-11-03T03:16:10.000Z",
            "latitude": 35.852349237999995,
            "longitude": 137.894030904,
            "altitude": 1010
        },
        {
            "time": "2023-11-03T03:16:12.000Z",
            "latitude": 35.852332572,
            "longitude": 137.89421423000002,
            "altitude": 1009
        },
        {
            "time": "2023-11-03T03:16:14.000Z",
            "latitude": 35.852332572,
            "longitude": 137.89436422400001,
            "altitude": 1009
        },
        {
            "time": "2023-11-03T03:16:16.000Z",
            "latitude": 35.852382569999996,
            "longitude": 137.894530884,
            "altitude": 1007
        },
        {
            "time": "2023-11-03T03:16:18.000Z",
            "latitude": 35.8524659,
            "longitude": 137.89473087599998,
            "altitude": 1006
        },
        {
            "time": "2023-11-03T03:16:20.000Z",
            "latitude": 35.85249923199999,
            "longitude": 137.894930868,
            "altitude": 1007
        },
        {
            "time": "2023-11-03T03:16:22.000Z",
            "latitude": 35.85253256399999,
            "longitude": 137.89504753,
            "altitude": 1005
        },
        {
            "time": "2023-11-03T03:16:24.000Z",
            "latitude": 35.85254923,
            "longitude": 137.895247522,
            "altitude": 1001
        },
        {
            "time": "2023-11-03T03:16:26.000Z",
            "latitude": 35.852582561999995,
            "longitude": 137.89541418200002,
            "altitude": 999
        },
        {
            "time": "2023-11-03T03:16:28.000Z",
            "latitude": 35.852565896,
            "longitude": 137.89556417600002,
            "altitude": 996
        },
        {
            "time": "2023-11-03T03:16:30.000Z",
            "latitude": 35.85249923199999,
            "longitude": 137.895730836,
            "altitude": 992
        },
        {
            "time": "2023-11-03T03:16:32.000Z",
            "latitude": 35.852382569999996,
            "longitude": 137.895830832,
            "altitude": 990
        },
        {
            "time": "2023-11-03T03:16:34.000Z",
            "latitude": 35.852232576000006,
            "longitude": 137.89589749600003,
            "altitude": 990
        },
        {
            "time": "2023-11-03T03:16:36.000Z",
            "latitude": 35.85208258200001,
            "longitude": 137.895980826,
            "altitude": 989
        },
        {
            "time": "2023-11-03T03:16:38.000Z",
            "latitude": 35.851949254,
            "longitude": 137.896080822,
            "altitude": 987
        },
        {
            "time": "2023-11-03T03:16:40.000Z",
            "latitude": 35.851765928,
            "longitude": 137.896014158,
            "altitude": 983
        },
        {
            "time": "2023-11-03T03:16:42.000Z",
            "latitude": 35.851582602,
            "longitude": 137.896014158,
            "altitude": 980
        },
        {
            "time": "2023-11-03T03:16:44.000Z",
            "latitude": 35.851415941999996,
            "longitude": 137.896030824,
            "altitude": 978
        },
        {
            "time": "2023-11-03T03:16:46.000Z",
            "latitude": 35.85133261200001,
            "longitude": 137.89624748199998,
            "altitude": 972
        },
        {
            "time": "2023-11-03T03:16:48.000Z",
            "latitude": 35.851349278,
            "longitude": 137.89638080999998,
            "altitude": 968
        },
        {
            "time": "2023-11-03T03:16:50.000Z",
            "latitude": 35.851399276,
            "longitude": 137.89654747,
            "altitude": 967
        },
        {
            "time": "2023-11-03T03:16:52.000Z",
            "latitude": 35.851482606000005,
            "longitude": 137.89678079400002,
            "altitude": 961
        },
        {
            "time": "2023-11-03T03:16:54.000Z",
            "latitude": 35.851515938000006,
            "longitude": 137.89691412200003,
            "altitude": 960
        },
        {
            "time": "2023-11-03T03:16:56.000Z",
            "latitude": 35.851532604,
            "longitude": 137.89706411600002,
            "altitude": 962
        },
        {
            "time": "2023-11-03T03:16:58.000Z",
            "latitude": 35.851482606000005,
            "longitude": 137.89724744199998,
            "altitude": 957
        },
        {
            "time": "2023-11-03T03:17:00.000Z",
            "latitude": 35.851399276,
            "longitude": 137.897430768,
            "altitude": 955
        },
        {
            "time": "2023-11-03T03:17:02.000Z",
            "latitude": 35.851399276,
            "longitude": 137.897580762,
            "altitude": 953
        },
        {
            "time": "2023-11-03T03:17:04.000Z",
            "latitude": 35.8516326,
            "longitude": 137.89759742799998,
            "altitude": 949
        },
        {
            "time": "2023-11-03T03:17:06.000Z",
            "latitude": 35.85178259400001,
            "longitude": 137.897564096,
            "altitude": 947
        },
        {
            "time": "2023-11-03T03:17:08.000Z",
            "latitude": 35.851949254,
            "longitude": 137.897530764,
            "altitude": 945
        },
        {
            "time": "2023-11-03T03:17:10.000Z",
            "latitude": 35.852115914,
            "longitude": 137.897530764,
            "altitude": 943
        },
        {
            "time": "2023-11-03T03:17:12.000Z",
            "latitude": 35.852282574,
            "longitude": 137.89754742999997,
            "altitude": 942
        },
        {
            "time": "2023-11-03T03:17:14.000Z",
            "latitude": 35.852432568,
            "longitude": 137.89759742799998,
            "altitude": 943
        },
        {
            "time": "2023-11-03T03:17:16.000Z",
            "latitude": 35.85253256399999,
            "longitude": 137.89763076,
            "altitude": 941
        },
        {
            "time": "2023-11-03T03:17:18.000Z",
            "latitude": 35.85263256,
            "longitude": 137.897730756,
            "altitude": 936
        },
        {
            "time": "2023-11-03T03:17:20.000Z",
            "latitude": 35.852699224,
            "longitude": 137.897914082,
            "altitude": 932
        },
        {
            "time": "2023-11-03T03:17:22.000Z",
            "latitude": 35.85253256399999,
            "longitude": 137.898080742,
            "altitude": 935
        },
        {
            "time": "2023-11-03T03:17:24.000Z",
            "latitude": 35.852382569999996,
            "longitude": 137.89803074399998,
            "altitude": 934
        },
        {
            "time": "2023-11-03T03:17:26.000Z",
            "latitude": 35.852232576000006,
            "longitude": 137.897914082,
            "altitude": 934
        },
        {
            "time": "2023-11-03T03:17:28.000Z",
            "latitude": 35.85208258200001,
            "longitude": 137.897897416,
            "altitude": 935
        },
        {
            "time": "2023-11-03T03:17:30.000Z",
            "latitude": 35.851899255999996,
            "longitude": 137.89788074999998,
            "altitude": 933
        },
        {
            "time": "2023-11-03T03:17:32.000Z",
            "latitude": 35.85174926199999,
            "longitude": 137.897864084,
            "altitude": 932
        },
        {
            "time": "2023-11-03T03:17:34.000Z",
            "latitude": 35.851582602,
            "longitude": 137.89798074600003,
            "altitude": 931
        },
        {
            "time": "2023-11-03T03:17:36.000Z",
            "latitude": 35.85171593,
            "longitude": 137.89823073600002,
            "altitude": 926
        },
        {
            "time": "2023-11-03T03:17:38.000Z",
            "latitude": 35.851982586,
            "longitude": 137.8982974,
            "altitude": 926
        },
        {
            "time": "2023-11-03T03:17:40.000Z",
            "latitude": 35.852115914,
            "longitude": 137.898347398,
            "altitude": 923
        },
        {
            "time": "2023-11-03T03:17:42.000Z",
            "latitude": 35.852232576000006,
            "longitude": 137.898347398,
            "altitude": 920
        },
        {
            "time": "2023-11-03T03:17:44.000Z",
            "latitude": 35.852282574,
            "longitude": 137.898514058,
            "altitude": 914
        },
        {
            "time": "2023-11-03T03:17:46.000Z",
            "latitude": 35.85221591,
            "longitude": 137.89873071600002,
            "altitude": 912
        },
        {
            "time": "2023-11-03T03:17:48.000Z",
            "latitude": 35.852032584,
            "longitude": 137.89879738,
            "altitude": 914
        },
        {
            "time": "2023-11-03T03:17:50.000Z",
            "latitude": 35.851999252000006,
            "longitude": 137.89888071000001,
            "altitude": 912
        },
        {
            "time": "2023-11-03T03:17:52.000Z",
            "latitude": 35.851915922,
            "longitude": 137.89896404,
            "altitude": 913
        },
        {
            "time": "2023-11-03T03:17:54.000Z",
            "latitude": 35.851815926,
            "longitude": 137.899080702,
            "altitude": 913
        },
        {
            "time": "2023-11-03T03:17:56.000Z",
            "latitude": 35.85204924999999,
            "longitude": 137.89921403,
            "altitude": 906
        },
        {
            "time": "2023-11-03T03:17:58.000Z",
            "latitude": 35.852182578000004,
            "longitude": 137.89916403200002,
            "altitude": 906
        },
        {
            "time": "2023-11-03T03:18:00.000Z",
            "latitude": 35.852315905999994,
            "longitude": 137.8991307,
            "altitude": 907
        },
        {
            "time": "2023-11-03T03:18:02.000Z",
            "latitude": 35.8524659,
            "longitude": 137.89934735799997,
            "altitude": 899
        },
        {
            "time": "2023-11-03T03:18:04.000Z",
            "latitude": 35.852565896,
            "longitude": 137.89948068600003,
            "altitude": 902
        },
        {
            "time": "2023-11-03T03:18:06.000Z",
            "latitude": 35.852665892000005,
            "longitude": 137.899564016,
            "altitude": 902
        },
        {
            "time": "2023-11-03T03:18:08.000Z",
            "latitude": 35.852765888,
            "longitude": 137.899697344,
            "altitude": 896
        },
        {
            "time": "2023-11-03T03:18:10.000Z",
            "latitude": 35.85288255,
            "longitude": 137.899847338,
            "altitude": 895
        },
        {
            "time": "2023-11-03T03:18:12.000Z",
            "latitude": 35.85296588,
            "longitude": 137.89996399999998,
            "altitude": 895
        },
        {
            "time": "2023-11-03T03:18:14.000Z",
            "latitude": 35.852949214,
            "longitude": 137.899980666,
            "altitude": 895
        },
        {
            "time": "2023-11-03T03:18:16.000Z",
            "latitude": 35.85296588,
            "longitude": 137.899997332,
            "altitude": 895
        },
        {
            "time": "2023-11-03T03:18:18.000Z",
            "latitude": 35.85298254599999,
            "longitude": 137.899997332,
            "altitude": 895
        },
        {
            "time": "2023-11-03T03:18:20.000Z",
            "latitude": 35.852999212,
            "longitude": 137.899980666,
            "altitude": 897
        },
        {
            "time": "2023-11-03T03:18:22.000Z",
            "latitude": 35.852999212,
            "longitude": 137.899980666,
            "altitude": 895
        },
        {
            "time": "2023-11-03T03:18:24.000Z",
            "latitude": 35.85298254599999,
            "longitude": 137.899980666,
            "altitude": 895
        },
        {
            "time": "2023-11-03T03:18:26.000Z",
            "latitude": 35.85298254599999,
            "longitude": 137.899980666,
            "altitude": 895
        },
        {
            "time": "2023-11-03T03:18:28.000Z",
            "latitude": 35.85298254599999,
            "longitude": 137.899980666,
            "altitude": 896
        },
        {
            "time": "2023-11-03T03:18:30.000Z",
            "latitude": 35.85298254599999,
            "longitude": 137.89996399999998,
            "altitude": 897
        },
        {
            "time": "2023-11-03T03:18:32.000Z",
            "latitude": 35.85298254599999,
            "longitude": 137.899980666,
            "altitude": 898
        },
        {
            "time": "2023-11-03T03:18:34.000Z",
            "latitude": 35.85296588,
            "longitude": 137.89996399999998,
            "altitude": 897
        },
        {
            "time": "2023-11-03T03:18:36.000Z",
            "latitude": 35.85296588,
            "longitude": 137.899980666,
            "altitude": 896
        },
        {
            "time": "2023-11-03T03:18:38.000Z",
            "latitude": 35.85298254599999,
            "longitude": 137.899980666,
            "altitude": 896
        },
        {
            "time": "2023-11-03T03:18:40.000Z",
            "latitude": 35.85298254599999,
            "longitude": 137.899980666,
            "altitude": 897
        },
        {
            "time": "2023-11-03T03:18:42.000Z",
            "latitude": 35.85298254599999,
            "longitude": 137.899980666,
            "altitude": 897
        }
    ],
    "pilotname": "yakisoba2",
    "distance": "2.2 km",
    "duration": "00:10:36",
    "activity": "Paraglider",
    "area": " S.E.T. Minami-Shinshu Hatobukiyama Paraglider Area"
}