{
    "track_points": [
        {
            "time": "2023-11-03T00:48:37.000Z",
            "latitude": 28.403967174,
            "longitude": 129.61179219399997,
            "altitude": 153
        },
        {
            "time": "2023-11-03T00:48:48.000Z",
            "latitude": 28.403683852,
            "longitude": 129.610742236,
            "altitude": 161
        },
        {
            "time": "2023-11-03T00:48:59.000Z",
            "latitude": 28.403117207999998,
            "longitude": 129.610075596,
            "altitude": 174
        },
        {
            "time": "2023-11-03T00:49:10.000Z",
            "latitude": 28.402667226000002,
            "longitude": 129.60940895599998,
            "altitude": 186
        },
        {
            "time": "2023-11-03T00:49:21.000Z",
            "latitude": 28.402133914,
            "longitude": 129.60889231000002,
            "altitude": 197
        },
        {
            "time": "2023-11-03T00:49:32.000Z",
            "latitude": 28.40156727,
            "longitude": 129.60880898,
            "altitude": 201
        },
        {
            "time": "2023-11-03T00:49:42.000Z",
            "latitude": 28.402250576,
            "longitude": 129.60930896,
            "altitude": 202
        },
        {
            "time": "2023-11-03T00:49:52.000Z",
            "latitude": 28.403100541999997,
            "longitude": 129.609792274,
            "altitude": 207
        },
        {
            "time": "2023-11-03T00:50:03.000Z",
            "latitude": 28.403417196,
            "longitude": 129.61054224400002,
            "altitude": 215
        },
        {
            "time": "2023-11-03T00:50:14.000Z",
            "latitude": 28.403600522,
            "longitude": 129.61130888000002,
            "altitude": 221
        },
        {
            "time": "2023-11-03T00:50:25.000Z",
            "latitude": 28.40373385,
            "longitude": 129.612008852,
            "altitude": 229
        },
        {
            "time": "2023-11-03T00:50:36.000Z",
            "latitude": 28.403750516000002,
            "longitude": 129.61255882999998,
            "altitude": 227
        },
        {
            "time": "2023-11-03T00:50:47.000Z",
            "latitude": 28.403233869999998,
            "longitude": 129.61177552799998,
            "altitude": 223
        },
        {
            "time": "2023-11-03T00:50:58.000Z",
            "latitude": 28.402700558,
            "longitude": 129.61082556600002,
            "altitude": 235
        },
        {
            "time": "2023-11-03T00:51:09.000Z",
            "latitude": 28.402100582,
            "longitude": 129.61014225999998,
            "altitude": 233
        },
        {
            "time": "2023-11-03T00:51:20.000Z",
            "latitude": 28.401433942,
            "longitude": 129.60947562,
            "altitude": 232
        },
        {
            "time": "2023-11-03T00:51:31.000Z",
            "latitude": 28.400767302,
            "longitude": 129.60879231399997,
            "altitude": 235
        },
        {
            "time": "2023-11-03T00:51:41.000Z",
            "latitude": 28.400100662,
            "longitude": 129.608425662,
            "altitude": 238
        },
        {
            "time": "2023-11-03T00:51:52.000Z",
            "latitude": 28.399367357999996,
            "longitude": 129.608242336,
            "altitude": 244
        },
        {
            "time": "2023-11-03T00:52:03.000Z",
            "latitude": 28.398734049999998,
            "longitude": 129.60815900600002,
            "altitude": 244
        },
        {
            "time": "2023-11-03T00:52:14.000Z",
            "latitude": 28.398117408000005,
            "longitude": 129.60814234,
            "altitude": 245
        },
        {
            "time": "2023-11-03T00:52:25.000Z",
            "latitude": 28.397534098,
            "longitude": 129.60814234,
            "altitude": 246
        },
        {
            "time": "2023-11-03T00:52:36.000Z",
            "latitude": 28.396867458000003,
            "longitude": 129.60789235,
            "altitude": 238
        },
        {
            "time": "2023-11-03T00:52:47.000Z",
            "latitude": 28.396250816000002,
            "longitude": 129.607692358,
            "altitude": 237
        },
        {
            "time": "2023-11-03T00:52:58.000Z",
            "latitude": 28.395650840000002,
            "longitude": 129.60757569600003,
            "altitude": 238
        },
        {
            "time": "2023-11-03T00:53:09.000Z",
            "latitude": 28.395200858000003,
            "longitude": 129.60775902199998,
            "altitude": 236
        },
        {
            "time": "2023-11-03T00:53:20.000Z",
            "latitude": 28.394717544000002,
            "longitude": 129.607959014,
            "altitude": 233
        },
        {
            "time": "2023-11-03T00:53:31.000Z",
            "latitude": 28.394167566,
            "longitude": 129.60805900999998,
            "altitude": 231
        },
        {
            "time": "2023-11-03T00:53:42.000Z",
            "latitude": 28.394517551999996,
            "longitude": 129.60860898800001,
            "altitude": 226
        },
        {
            "time": "2023-11-03T00:53:52.000Z",
            "latitude": 28.395084196,
            "longitude": 129.60905897,
            "altitude": 227
        },
        {
            "time": "2023-11-03T00:54:02.000Z",
            "latitude": 28.396217483999997,
            "longitude": 129.608908976,
            "altitude": 223
        },
        {
            "time": "2023-11-03T00:54:12.000Z",
            "latitude": 28.397350772000003,
            "longitude": 129.608625654,
            "altitude": 221
        },
        {
            "time": "2023-11-03T00:54:22.000Z",
            "latitude": 28.398467394,
            "longitude": 129.60847566,
            "altitude": 227
        },
        {
            "time": "2023-11-03T00:54:33.000Z",
            "latitude": 28.39956735,
            "longitude": 129.60864231999997,
            "altitude": 238
        },
        {
            "time": "2023-11-03T00:54:44.000Z",
            "latitude": 28.400583976,
            "longitude": 129.60889231000002,
            "altitude": 245
        },
        {
            "time": "2023-11-03T00:54:55.000Z",
            "latitude": 28.401400610000003,
            "longitude": 129.60937562400002,
            "altitude": 246
        },
        {
            "time": "2023-11-03T00:55:06.000Z",
            "latitude": 28.402050584,
            "longitude": 129.610025598,
            "altitude": 251
        },
        {
            "time": "2023-11-03T00:55:17.000Z",
            "latitude": 28.402367238000004,
            "longitude": 129.610708904,
            "altitude": 253
        },
        {
            "time": "2023-11-03T00:55:28.000Z",
            "latitude": 28.402033918000004,
            "longitude": 129.61077556799998,
            "altitude": 253
        },
        {
            "time": "2023-11-03T00:55:39.000Z",
            "latitude": 28.401683931999997,
            "longitude": 129.60965894600002,
            "altitude": 251
        },
        {
            "time": "2023-11-03T00:55:50.000Z",
            "latitude": 28.402517232,
            "longitude": 129.609458954,
            "altitude": 250
        },
        {
            "time": "2023-11-03T00:56:00.000Z",
            "latitude": 28.402650559999998,
            "longitude": 129.610042264,
            "altitude": 251
        },
        {
            "time": "2023-11-03T00:56:10.000Z",
            "latitude": 28.403033878,
            "longitude": 129.610658906,
            "altitude": 251
        },
        {
            "time": "2023-11-03T00:56:20.000Z",
            "latitude": 28.403050544,
            "longitude": 129.61087556399997,
            "altitude": 256
        },
        {
            "time": "2023-11-03T00:56:30.000Z",
            "latitude": 28.402600562,
            "longitude": 129.61005893,
            "altitude": 254
        },
        {
            "time": "2023-11-03T00:56:40.000Z",
            "latitude": 28.402200578000002,
            "longitude": 129.609208964,
            "altitude": 256
        },
        {
            "time": "2023-11-03T00:56:51.000Z",
            "latitude": 28.402183912,
            "longitude": 129.60969227799998,
            "altitude": 258
        },
        {
            "time": "2023-11-03T00:57:02.000Z",
            "latitude": 28.403100541999997,
            "longitude": 129.61005893,
            "altitude": 257
        },
        {
            "time": "2023-11-03T00:57:13.000Z",
            "latitude": 28.403767182000003,
            "longitude": 129.610692238,
            "altitude": 257
        },
        {
            "time": "2023-11-03T00:57:24.000Z",
            "latitude": 28.403467194,
            "longitude": 129.61090889599998,
            "altitude": 256
        },
        {
            "time": "2023-11-03T00:57:35.000Z",
            "latitude": 28.403233869999998,
            "longitude": 129.61134221199998,
            "altitude": 265
        },
        {
            "time": "2023-11-03T00:57:46.000Z",
            "latitude": 28.402700558,
            "longitude": 129.61120888399998,
            "altitude": 269
        },
        {
            "time": "2023-11-03T00:57:57.000Z",
            "latitude": 28.402200578000002,
            "longitude": 129.610375584,
            "altitude": 270
        },
        {
            "time": "2023-11-03T00:58:08.000Z",
            "latitude": 28.401683931999997,
            "longitude": 129.60935895800003,
            "altitude": 272
        },
        {
            "time": "2023-11-03T00:58:18.000Z",
            "latitude": 28.401083955999997,
            "longitude": 129.60877564800003,
            "altitude": 275
        },
        {
            "time": "2023-11-03T00:58:28.000Z",
            "latitude": 28.400517312,
            "longitude": 129.608525658,
            "altitude": 277
        }
    ],
    "pilotname": "Yukorin",
    "distance": "1.1 km",
    "duration": "00:09:51",
    "activity": "Paraglider"
}